{
    "0": [
        "{\"type\": \"write\", \"url\": \"/api/v1/orderOtherService/orderOther\", \"body\": \"{\\\"id\\\":\\\"76848992-e26e-4168-8c0e-30ce2a32354a\\\",\\\"boughtDate\\\":\\\"2024-05-09 18:31:54\\\",\\\"travelDate\\\":\\\"2024-05-09\\\",\\\"travelTime\\\":\\\"2013-05-04 09:51:52\\\",\\\"accountId\\\":\\\"4d2a46c7-71cb-4cf1-b5bb-b68406d9da6f\\\",\\\"contactsName\\\":\\\"Contacts_One\\\",\\\"documentType\\\":1,\\\"contactsDocumentNumber\\\":\\\"DocumentNumber_One\\\",\\\"trainNumber\\\":\\\"Z1234\\\",\\\"coachNumber\\\":5,\\\"seatClass\\\":2,\\\"seatNumber\\\":\\\"145098254\\\",\\\"from\\\":\\\"shanghai\\\",\\\"to\\\":\\\"nanjing\\\",\\\"status\\\":0,\\\"price\\\":\\\"350.0\\\",\\\"differenceMoney\\\":\\\"0.0\\\"}\", \"method\": \"POST\"}",
        "{\"type\": \"write\", \"url\": \"/api/v1/orderOtherService/orderOther\", \"body\": \"{\\\"id\\\":\\\"0909b313-eeab-4463-a068-82f33d56cb49\\\",\\\"boughtDate\\\":\\\"2024-05-09 18:31:54\\\",\\\"travelDate\\\":\\\"2024-05-09\\\",\\\"travelTime\\\":\\\"2013-05-04 09:51:52\\\",\\\"accountId\\\":\\\"4d2a46c7-71cb-4cf1-b5bb-b68406d9da6f\\\",\\\"contactsName\\\":\\\"Contacts_One\\\",\\\"documentType\\\":1,\\\"contactsDocumentNumber\\\":\\\"DocumentNumber_One\\\",\\\"trainNumber\\\":\\\"Z1234\\\",\\\"coachNumber\\\":5,\\\"seatClass\\\":2,\\\"seatNumber\\\":\\\"145098254\\\",\\\"from\\\":\\\"shanghai\\\",\\\"to\\\":\\\"nanjing\\\",\\\"status\\\":4,\\\"price\\\":\\\"350.0\\\",\\\"differenceMoney\\\":\\\"0.0\\\"}\", \"method\": \"PUT\"}"
    ],
    "1": [
        "{\"type\": \"write\", \"url\": \"/api/v1/orderOtherService/orderOther\", \"body\": \"{\\\"id\\\":\\\"76848992-e26e-4168-8c0e-30ce2a32354a\\\",\\\"boughtDate\\\":\\\"2024-05-09 18:31:54\\\",\\\"travelDate\\\":\\\"2024-05-09\\\",\\\"travelTime\\\":\\\"2013-05-04 09:51:52\\\",\\\"accountId\\\":\\\"4d2a46c7-71cb-4cf1-b5bb-b68406d9da6f\\\",\\\"contactsName\\\":\\\"Contacts_One\\\",\\\"documentType\\\":1,\\\"contactsDocumentNumber\\\":\\\"DocumentNumber_One\\\",\\\"trainNumber\\\":\\\"Z1234\\\",\\\"coachNumber\\\":5,\\\"seatClass\\\":2,\\\"seatNumber\\\":\\\"145098254\\\",\\\"from\\\":\\\"shanghai\\\",\\\"to\\\":\\\"nanjing\\\",\\\"status\\\":0,\\\"price\\\":\\\"350.0\\\",\\\"differenceMoney\\\":\\\"0.0\\\"}\", \"method\": \"POST\"}",
        "{\"type\": \"write\", \"url\": \"/api/v1/orderOtherService/orderOther\", \"body\": \"{\\\"id\\\":\\\"0909b313-eeab-4463-a068-82f33d56cb49\\\",\\\"boughtDate\\\":\\\"2024-05-09 18:31:54\\\",\\\"travelDate\\\":\\\"2024-05-09\\\",\\\"travelTime\\\":\\\"2013-05-04 09:51:52\\\",\\\"accountId\\\":\\\"4d2a46c7-71cb-4cf1-b5bb-b68406d9da6f\\\",\\\"contactsName\\\":\\\"Contacts_One\\\",\\\"documentType\\\":1,\\\"contactsDocumentNumber\\\":\\\"DocumentNumber_One\\\",\\\"trainNumber\\\":\\\"Z1234\\\",\\\"coachNumber\\\":5,\\\"seatClass\\\":2,\\\"seatNumber\\\":\\\"145098254\\\",\\\"from\\\":\\\"shanghai\\\",\\\"to\\\":\\\"nanjing\\\",\\\"status\\\":7,\\\"price\\\":\\\"350.0\\\",\\\"differenceMoney\\\":\\\"0.0\\\"}\", \"method\": \"PUT\"}"
    ],
    "2": [
        "{\"type\": \"write\", \"url\": \"/api/v1/orderOtherService/orderOther\", \"body\": \"{\\\"id\\\":\\\"76848992-e26e-4168-8c0e-30ce2a32354a\\\",\\\"boughtDate\\\":\\\"2024-05-09 18:31:54\\\",\\\"travelDate\\\":\\\"2024-05-09\\\",\\\"travelTime\\\":\\\"2013-05-04 09:51:52\\\",\\\"accountId\\\":\\\"4d2a46c7-71cb-4cf1-b5bb-b68406d9da6f\\\",\\\"contactsName\\\":\\\"Contacts_One\\\",\\\"documentType\\\":1,\\\"contactsDocumentNumber\\\":\\\"DocumentNumber_One\\\",\\\"trainNumber\\\":\\\"Z1234\\\",\\\"coachNumber\\\":5,\\\"seatClass\\\":2,\\\"seatNumber\\\":\\\"145098254\\\",\\\"from\\\":\\\"shanghai\\\",\\\"to\\\":\\\"nanjing\\\",\\\"status\\\":0,\\\"price\\\":\\\"350.0\\\",\\\"differenceMoney\\\":\\\"0.0\\\"}\", \"method\": \"POST\"}",
        "{\"type\": \"write\", \"url\": \"/api/v1/orderOtherService/orderOther/status/?/?\", \"body\": \"\", \"method\": \"GET\"}"
    ],
    "3": [
        "{\"type\": \"write\", \"url\": \"/api/v1/orderOtherService/orderOther\", \"body\": \"{\\\"id\\\":\\\"0909b313-eeab-4463-a068-82f33d56cb49\\\",\\\"boughtDate\\\":\\\"2024-05-09 18:31:54\\\",\\\"travelDate\\\":\\\"2024-05-09\\\",\\\"travelTime\\\":\\\"2013-05-04 09:51:52\\\",\\\"accountId\\\":\\\"4d2a46c7-71cb-4cf1-b5bb-b68406d9da6f\\\",\\\"contactsName\\\":\\\"Contacts_One\\\",\\\"documentType\\\":1,\\\"contactsDocumentNumber\\\":\\\"DocumentNumber_One\\\",\\\"trainNumber\\\":\\\"Z1234\\\",\\\"coachNumber\\\":5,\\\"seatClass\\\":2,\\\"seatNumber\\\":\\\"145098254\\\",\\\"from\\\":\\\"shanghai\\\",\\\"to\\\":\\\"nanjing\\\",\\\"status\\\":4,\\\"price\\\":\\\"350.0\\\",\\\"differenceMoney\\\":\\\"0.0\\\"}\", \"method\": \"PUT\"}",
        "{\"type\": \"write\", \"url\": \"/api/v1/orderOtherService/orderOther\", \"body\": \"{\\\"id\\\":\\\"0909b313-eeab-4463-a068-82f33d56cb49\\\",\\\"boughtDate\\\":\\\"2024-05-09 18:31:54\\\",\\\"travelDate\\\":\\\"2024-05-09\\\",\\\"travelTime\\\":\\\"2013-05-04 09:51:52\\\",\\\"accountId\\\":\\\"4d2a46c7-71cb-4cf1-b5bb-b68406d9da6f\\\",\\\"contactsName\\\":\\\"Contacts_One\\\",\\\"documentType\\\":1,\\\"contactsDocumentNumber\\\":\\\"DocumentNumber_One\\\",\\\"trainNumber\\\":\\\"Z1234\\\",\\\"coachNumber\\\":5,\\\"seatClass\\\":2,\\\"seatNumber\\\":\\\"145098254\\\",\\\"from\\\":\\\"shanghai\\\",\\\"to\\\":\\\"nanjing\\\",\\\"status\\\":7,\\\"price\\\":\\\"350.0\\\",\\\"differenceMoney\\\":\\\"0.0\\\"}\", \"method\": \"PUT\"}"
    ],
    "4": [
        "{\"type\": \"write\", \"url\": \"/api/v1/orderOtherService/orderOther\", \"body\": \"{\\\"id\\\":\\\"0909b313-eeab-4463-a068-82f33d56cb49\\\",\\\"boughtDate\\\":\\\"2024-05-09 18:31:54\\\",\\\"travelDate\\\":\\\"2024-05-09\\\",\\\"travelTime\\\":\\\"2013-05-04 09:51:52\\\",\\\"accountId\\\":\\\"4d2a46c7-71cb-4cf1-b5bb-b68406d9da6f\\\",\\\"contactsName\\\":\\\"Contacts_One\\\",\\\"documentType\\\":1,\\\"contactsDocumentNumber\\\":\\\"DocumentNumber_One\\\",\\\"trainNumber\\\":\\\"Z1234\\\",\\\"coachNumber\\\":5,\\\"seatClass\\\":2,\\\"seatNumber\\\":\\\"145098254\\\",\\\"from\\\":\\\"shanghai\\\",\\\"to\\\":\\\"nanjing\\\",\\\"status\\\":4,\\\"price\\\":\\\"350.0\\\",\\\"differenceMoney\\\":\\\"0.0\\\"}\", \"method\": \"PUT\"}",
        "{\"type\": \"write\", \"url\": \"/api/v1/orderOtherService/orderOther/status/?/?\", \"body\": \"\", \"method\": \"GET\"}"
    ],
    "5": [
        "{\"type\": \"write\", \"url\": \"/api/v1/orderOtherService/orderOther\", \"body\": \"{\\\"id\\\":\\\"0909b313-eeab-4463-a068-82f33d56cb49\\\",\\\"boughtDate\\\":\\\"2024-05-09 18:31:54\\\",\\\"travelDate\\\":\\\"2024-05-09\\\",\\\"travelTime\\\":\\\"2013-05-04 09:51:52\\\",\\\"accountId\\\":\\\"4d2a46c7-71cb-4cf1-b5bb-b68406d9da6f\\\",\\\"contactsName\\\":\\\"Contacts_One\\\",\\\"documentType\\\":1,\\\"contactsDocumentNumber\\\":\\\"DocumentNumber_One\\\",\\\"trainNumber\\\":\\\"Z1234\\\",\\\"coachNumber\\\":5,\\\"seatClass\\\":2,\\\"seatNumber\\\":\\\"145098254\\\",\\\"from\\\":\\\"shanghai\\\",\\\"to\\\":\\\"nanjing\\\",\\\"status\\\":7,\\\"price\\\":\\\"350.0\\\",\\\"differenceMoney\\\":\\\"0.0\\\"}\", \"method\": \"PUT\"}",
        "{\"type\": \"write\", \"url\": \"/api/v1/orderOtherService/orderOther/status/?/?\", \"body\": \"\", \"method\": \"GET\"}"
    ],
    "6": [
        "{\"type\": \"read\", \"url\": \"/api/v1/users/login\", \"body\": \"\", \"method\": \"POST\"}",
        "{\"type\": \"write\", \"url\": \"/api/v1/orderOtherService/orderOther\", \"body\": \"{\\\"id\\\":\\\"76848992-e26e-4168-8c0e-30ce2a32354a\\\",\\\"boughtDate\\\":\\\"2024-05-09 18:31:54\\\",\\\"travelDate\\\":\\\"2024-05-09\\\",\\\"travelTime\\\":\\\"2013-05-04 09:51:52\\\",\\\"accountId\\\":\\\"4d2a46c7-71cb-4cf1-b5bb-b68406d9da6f\\\",\\\"contactsName\\\":\\\"Contacts_One\\\",\\\"documentType\\\":1,\\\"contactsDocumentNumber\\\":\\\"DocumentNumber_One\\\",\\\"trainNumber\\\":\\\"Z1234\\\",\\\"coachNumber\\\":5,\\\"seatClass\\\":2,\\\"seatNumber\\\":\\\"145098254\\\",\\\"from\\\":\\\"shanghai\\\",\\\"to\\\":\\\"nanjing\\\",\\\"status\\\":0,\\\"price\\\":\\\"350.0\\\",\\\"differenceMoney\\\":\\\"0.0\\\"}\", \"method\": \"POST\"}"
    ],
    "7": [
        "{\"type\": \"read\", \"url\": \"/api/v1/users/login\", \"body\": \"\", \"method\": \"POST\"}",
        "{\"type\": \"write\", \"url\": \"/api/v1/orderOtherService/orderOther\", \"body\": \"{\\\"id\\\":\\\"0909b313-eeab-4463-a068-82f33d56cb49\\\",\\\"boughtDate\\\":\\\"2024-05-09 18:31:54\\\",\\\"travelDate\\\":\\\"2024-05-09\\\",\\\"travelTime\\\":\\\"2013-05-04 09:51:52\\\",\\\"accountId\\\":\\\"4d2a46c7-71cb-4cf1-b5bb-b68406d9da6f\\\",\\\"contactsName\\\":\\\"Contacts_One\\\",\\\"documentType\\\":1,\\\"contactsDocumentNumber\\\":\\\"DocumentNumber_One\\\",\\\"trainNumber\\\":\\\"Z1234\\\",\\\"coachNumber\\\":5,\\\"seatClass\\\":2,\\\"seatNumber\\\":\\\"145098254\\\",\\\"from\\\":\\\"shanghai\\\",\\\"to\\\":\\\"nanjing\\\",\\\"status\\\":4,\\\"price\\\":\\\"350.0\\\",\\\"differenceMoney\\\":\\\"0.0\\\"}\", \"method\": \"PUT\"}"
    ],
    "8": [
        "{\"type\": \"read\", \"url\": \"/api/v1/users/login\", \"body\": \"\", \"method\": \"POST\"}",
        "{\"type\": \"write\", \"url\": \"/api/v1/orderOtherService/orderOther\", \"body\": \"{\\\"id\\\":\\\"0909b313-eeab-4463-a068-82f33d56cb49\\\",\\\"boughtDate\\\":\\\"2024-05-09 18:31:54\\\",\\\"travelDate\\\":\\\"2024-05-09\\\",\\\"travelTime\\\":\\\"2013-05-04 09:51:52\\\",\\\"accountId\\\":\\\"4d2a46c7-71cb-4cf1-b5bb-b68406d9da6f\\\",\\\"contactsName\\\":\\\"Contacts_One\\\",\\\"documentType\\\":1,\\\"contactsDocumentNumber\\\":\\\"DocumentNumber_One\\\",\\\"trainNumber\\\":\\\"Z1234\\\",\\\"coachNumber\\\":5,\\\"seatClass\\\":2,\\\"seatNumber\\\":\\\"145098254\\\",\\\"from\\\":\\\"shanghai\\\",\\\"to\\\":\\\"nanjing\\\",\\\"status\\\":7,\\\"price\\\":\\\"350.0\\\",\\\"differenceMoney\\\":\\\"0.0\\\"}\", \"method\": \"PUT\"}"
    ],
    "9": [
        "{\"type\": \"read\", \"url\": \"/api/v1/users/login\", \"body\": \"\", \"method\": \"POST\"}",
        "{\"type\": \"write\", \"url\": \"/api/v1/inside_pay_service/inside_payment/drawback/?/?\", \"body\": \"\", \"method\": \"GET\"}"
    ],
    "10": [
        "{\"type\": \"read\", \"url\": \"/api/v1/users/login\", \"body\": \"\", \"method\": \"POST\"}",
        "{\"type\": \"write\", \"url\": \"/api/v1/orderOtherService/orderOther/status/?/?\", \"body\": \"\", \"method\": \"GET\"}"
    ],
    "11": [
        "{\"type\": \"read\", \"url\": \"/api/v1/orderservice/order/security/?/?\", \"body\": \"\", \"method\": \"GET\"}",
        "{\"type\": \"write\", \"url\": \"/api/v1/orderOtherService/orderOther\", \"body\": \"{\\\"id\\\":\\\"76848992-e26e-4168-8c0e-30ce2a32354a\\\",\\\"boughtDate\\\":\\\"2024-05-09 18:31:54\\\",\\\"travelDate\\\":\\\"2024-05-09\\\",\\\"travelTime\\\":\\\"2013-05-04 09:51:52\\\",\\\"accountId\\\":\\\"4d2a46c7-71cb-4cf1-b5bb-b68406d9da6f\\\",\\\"contactsName\\\":\\\"Contacts_One\\\",\\\"documentType\\\":1,\\\"contactsDocumentNumber\\\":\\\"DocumentNumber_One\\\",\\\"trainNumber\\\":\\\"Z1234\\\",\\\"coachNumber\\\":5,\\\"seatClass\\\":2,\\\"seatNumber\\\":\\\"145098254\\\",\\\"from\\\":\\\"shanghai\\\",\\\"to\\\":\\\"nanjing\\\",\\\"status\\\":0,\\\"price\\\":\\\"350.0\\\",\\\"differenceMoney\\\":\\\"0.0\\\"}\", \"method\": \"POST\"}"
    ],
    "12": [
        "{\"type\": \"read\", \"url\": \"/api/v1/orderservice/order/security/?/?\", \"body\": \"\", \"method\": \"GET\"}",
        "{\"type\": \"write\", \"url\": \"/api/v1/orderOtherService/orderOther\", \"body\": \"{\\\"id\\\":\\\"0909b313-eeab-4463-a068-82f33d56cb49\\\",\\\"boughtDate\\\":\\\"2024-05-09 18:31:54\\\",\\\"travelDate\\\":\\\"2024-05-09\\\",\\\"travelTime\\\":\\\"2013-05-04 09:51:52\\\",\\\"accountId\\\":\\\"4d2a46c7-71cb-4cf1-b5bb-b68406d9da6f\\\",\\\"contactsName\\\":\\\"Contacts_One\\\",\\\"documentType\\\":1,\\\"contactsDocumentNumber\\\":\\\"DocumentNumber_One\\\",\\\"trainNumber\\\":\\\"Z1234\\\",\\\"coachNumber\\\":5,\\\"seatClass\\\":2,\\\"seatNumber\\\":\\\"145098254\\\",\\\"from\\\":\\\"shanghai\\\",\\\"to\\\":\\\"nanjing\\\",\\\"status\\\":4,\\\"price\\\":\\\"350.0\\\",\\\"differenceMoney\\\":\\\"0.0\\\"}\", \"method\": \"PUT\"}"
    ],
    "13": [
        "{\"type\": \"read\", \"url\": \"/api/v1/orderservice/order/security/?/?\", \"body\": \"\", \"method\": \"GET\"}",
        "{\"type\": \"write\", \"url\": \"/api/v1/orderOtherService/orderOther\", \"body\": \"{\\\"id\\\":\\\"0909b313-eeab-4463-a068-82f33d56cb49\\\",\\\"boughtDate\\\":\\\"2024-05-09 18:31:54\\\",\\\"travelDate\\\":\\\"2024-05-09\\\",\\\"travelTime\\\":\\\"2013-05-04 09:51:52\\\",\\\"accountId\\\":\\\"4d2a46c7-71cb-4cf1-b5bb-b68406d9da6f\\\",\\\"contactsName\\\":\\\"Contacts_One\\\",\\\"documentType\\\":1,\\\"contactsDocumentNumber\\\":\\\"DocumentNumber_One\\\",\\\"trainNumber\\\":\\\"Z1234\\\",\\\"coachNumber\\\":5,\\\"seatClass\\\":2,\\\"seatNumber\\\":\\\"145098254\\\",\\\"from\\\":\\\"shanghai\\\",\\\"to\\\":\\\"nanjing\\\",\\\"status\\\":7,\\\"price\\\":\\\"350.0\\\",\\\"differenceMoney\\\":\\\"0.0\\\"}\", \"method\": \"PUT\"}"
    ],
    "14": [
        "{\"type\": \"read\", \"url\": \"/api/v1/orderservice/order/security/?/?\", \"body\": \"\", \"method\": \"GET\"}",
        "{\"type\": \"write\", \"url\": \"/api/v1/inside_pay_service/inside_payment/drawback/?/?\", \"body\": \"\", \"method\": \"GET\"}"
    ],
    "15": [
        "{\"type\": \"read\", \"url\": \"/api/v1/orderservice/order/security/?/?\", \"body\": \"\", \"method\": \"GET\"}",
        "{\"type\": \"write\", \"url\": \"/api/v1/orderOtherService/orderOther/status/?/?\", \"body\": \"\", \"method\": \"GET\"}"
    ],
    "16": [
        "{\"type\": \"read\", \"url\": \"/api/v1/orderOtherService/orderOther/security/?/?\", \"body\": \"\", \"method\": \"GET\"}",
        "{\"type\": \"write\", \"url\": \"/api/v1/orderOtherService/orderOther\", \"body\": \"{\\\"id\\\":\\\"76848992-e26e-4168-8c0e-30ce2a32354a\\\",\\\"boughtDate\\\":\\\"2024-05-09 18:31:54\\\",\\\"travelDate\\\":\\\"2024-05-09\\\",\\\"travelTime\\\":\\\"2013-05-04 09:51:52\\\",\\\"accountId\\\":\\\"4d2a46c7-71cb-4cf1-b5bb-b68406d9da6f\\\",\\\"contactsName\\\":\\\"Contacts_One\\\",\\\"documentType\\\":1,\\\"contactsDocumentNumber\\\":\\\"DocumentNumber_One\\\",\\\"trainNumber\\\":\\\"Z1234\\\",\\\"coachNumber\\\":5,\\\"seatClass\\\":2,\\\"seatNumber\\\":\\\"145098254\\\",\\\"from\\\":\\\"shanghai\\\",\\\"to\\\":\\\"nanjing\\\",\\\"status\\\":0,\\\"price\\\":\\\"350.0\\\",\\\"differenceMoney\\\":\\\"0.0\\\"}\", \"method\": \"POST\"}"
    ],
    "17": [
        "{\"type\": \"read\", \"url\": \"/api/v1/orderOtherService/orderOther/security/?/?\", \"body\": \"\", \"method\": \"GET\"}",
        "{\"type\": \"write\", \"url\": \"/api/v1/orderOtherService/orderOther\", \"body\": \"{\\\"id\\\":\\\"0909b313-eeab-4463-a068-82f33d56cb49\\\",\\\"boughtDate\\\":\\\"2024-05-09 18:31:54\\\",\\\"travelDate\\\":\\\"2024-05-09\\\",\\\"travelTime\\\":\\\"2013-05-04 09:51:52\\\",\\\"accountId\\\":\\\"4d2a46c7-71cb-4cf1-b5bb-b68406d9da6f\\\",\\\"contactsName\\\":\\\"Contacts_One\\\",\\\"documentType\\\":1,\\\"contactsDocumentNumber\\\":\\\"DocumentNumber_One\\\",\\\"trainNumber\\\":\\\"Z1234\\\",\\\"coachNumber\\\":5,\\\"seatClass\\\":2,\\\"seatNumber\\\":\\\"145098254\\\",\\\"from\\\":\\\"shanghai\\\",\\\"to\\\":\\\"nanjing\\\",\\\"status\\\":4,\\\"price\\\":\\\"350.0\\\",\\\"differenceMoney\\\":\\\"0.0\\\"}\", \"method\": \"PUT\"}"
    ],
    "18": [
        "{\"type\": \"read\", \"url\": \"/api/v1/orderOtherService/orderOther/security/?/?\", \"body\": \"\", \"method\": \"GET\"}",
        "{\"type\": \"write\", \"url\": \"/api/v1/orderOtherService/orderOther\", \"body\": \"{\\\"id\\\":\\\"0909b313-eeab-4463-a068-82f33d56cb49\\\",\\\"boughtDate\\\":\\\"2024-05-09 18:31:54\\\",\\\"travelDate\\\":\\\"2024-05-09\\\",\\\"travelTime\\\":\\\"2013-05-04 09:51:52\\\",\\\"accountId\\\":\\\"4d2a46c7-71cb-4cf1-b5bb-b68406d9da6f\\\",\\\"contactsName\\\":\\\"Contacts_One\\\",\\\"documentType\\\":1,\\\"contactsDocumentNumber\\\":\\\"DocumentNumber_One\\\",\\\"trainNumber\\\":\\\"Z1234\\\",\\\"coachNumber\\\":5,\\\"seatClass\\\":2,\\\"seatNumber\\\":\\\"145098254\\\",\\\"from\\\":\\\"shanghai\\\",\\\"to\\\":\\\"nanjing\\\",\\\"status\\\":7,\\\"price\\\":\\\"350.0\\\",\\\"differenceMoney\\\":\\\"0.0\\\"}\", \"method\": \"PUT\"}"
    ],
    "19": [
        "{\"type\": \"read\", \"url\": \"/api/v1/orderOtherService/orderOther/security/?/?\", \"body\": \"\", \"method\": \"GET\"}",
        "{\"type\": \"write\", \"url\": \"/api/v1/inside_pay_service/inside_payment/drawback/?/?\", \"body\": \"\", \"method\": \"GET\"}"
    ],
    "20": [
        "{\"type\": \"read\", \"url\": \"/api/v1/orderOtherService/orderOther/security/?/?\", \"body\": \"\", \"method\": \"GET\"}",
        "{\"type\": \"write\", \"url\": \"/api/v1/orderOtherService/orderOther/status/?/?\", \"body\": \"\", \"method\": \"GET\"}"
    ],
    "21": [
        "{\"type\": \"read\", \"url\": \"/api/v1/orderOtherService/orderOther\", \"body\": \"{\\\"id\\\":\\\"76848992-e26e-4168-8c0e-30ce2a32354a\\\",\\\"boughtDate\\\":\\\"2024-05-09 18:31:54\\\",\\\"travelDate\\\":\\\"2024-05-09\\\",\\\"travelTime\\\":\\\"2013-05-04 09:51:52\\\",\\\"accountId\\\":\\\"4d2a46c7-71cb-4cf1-b5bb-b68406d9da6f\\\",\\\"contactsName\\\":\\\"Contacts_One\\\",\\\"documentType\\\":1,\\\"contactsDocumentNumber\\\":\\\"DocumentNumber_One\\\",\\\"trainNumber\\\":\\\"Z1234\\\",\\\"coachNumber\\\":5,\\\"seatClass\\\":2,\\\"seatNumber\\\":\\\"145098254\\\",\\\"from\\\":\\\"shanghai\\\",\\\"to\\\":\\\"nanjing\\\",\\\"status\\\":0,\\\"price\\\":\\\"350.0\\\",\\\"differenceMoney\\\":\\\"0.0\\\"}\", \"method\": \"POST\"}",
        "{\"type\": \"write\", \"url\": \"/api/v1/orderOtherService/orderOther\", \"body\": \"{\\\"id\\\":\\\"0909b313-eeab-4463-a068-82f33d56cb49\\\",\\\"boughtDate\\\":\\\"2024-05-09 18:31:54\\\",\\\"travelDate\\\":\\\"2024-05-09\\\",\\\"travelTime\\\":\\\"2013-05-04 09:51:52\\\",\\\"accountId\\\":\\\"4d2a46c7-71cb-4cf1-b5bb-b68406d9da6f\\\",\\\"contactsName\\\":\\\"Contacts_One\\\",\\\"documentType\\\":1,\\\"contactsDocumentNumber\\\":\\\"DocumentNumber_One\\\",\\\"trainNumber\\\":\\\"Z1234\\\",\\\"coachNumber\\\":5,\\\"seatClass\\\":2,\\\"seatNumber\\\":\\\"145098254\\\",\\\"from\\\":\\\"shanghai\\\",\\\"to\\\":\\\"nanjing\\\",\\\"status\\\":4,\\\"price\\\":\\\"350.0\\\",\\\"differenceMoney\\\":\\\"0.0\\\"}\", \"method\": \"PUT\"}"
    ],
    "22": [
        "{\"type\": \"read\", \"url\": \"/api/v1/orderOtherService/orderOther\", \"body\": \"{\\\"id\\\":\\\"76848992-e26e-4168-8c0e-30ce2a32354a\\\",\\\"boughtDate\\\":\\\"2024-05-09 18:31:54\\\",\\\"travelDate\\\":\\\"2024-05-09\\\",\\\"travelTime\\\":\\\"2013-05-04 09:51:52\\\",\\\"accountId\\\":\\\"4d2a46c7-71cb-4cf1-b5bb-b68406d9da6f\\\",\\\"contactsName\\\":\\\"Contacts_One\\\",\\\"documentType\\\":1,\\\"contactsDocumentNumber\\\":\\\"DocumentNumber_One\\\",\\\"trainNumber\\\":\\\"Z1234\\\",\\\"coachNumber\\\":5,\\\"seatClass\\\":2,\\\"seatNumber\\\":\\\"145098254\\\",\\\"from\\\":\\\"shanghai\\\",\\\"to\\\":\\\"nanjing\\\",\\\"status\\\":0,\\\"price\\\":\\\"350.0\\\",\\\"differenceMoney\\\":\\\"0.0\\\"}\", \"method\": \"POST\"}",
        "{\"type\": \"write\", \"url\": \"/api/v1/orderOtherService/orderOther\", \"body\": \"{\\\"id\\\":\\\"0909b313-eeab-4463-a068-82f33d56cb49\\\",\\\"boughtDate\\\":\\\"2024-05-09 18:31:54\\\",\\\"travelDate\\\":\\\"2024-05-09\\\",\\\"travelTime\\\":\\\"2013-05-04 09:51:52\\\",\\\"accountId\\\":\\\"4d2a46c7-71cb-4cf1-b5bb-b68406d9da6f\\\",\\\"contactsName\\\":\\\"Contacts_One\\\",\\\"documentType\\\":1,\\\"contactsDocumentNumber\\\":\\\"DocumentNumber_One\\\",\\\"trainNumber\\\":\\\"Z1234\\\",\\\"coachNumber\\\":5,\\\"seatClass\\\":2,\\\"seatNumber\\\":\\\"145098254\\\",\\\"from\\\":\\\"shanghai\\\",\\\"to\\\":\\\"nanjing\\\",\\\"status\\\":7,\\\"price\\\":\\\"350.0\\\",\\\"differenceMoney\\\":\\\"0.0\\\"}\", \"method\": \"PUT\"}"
    ],
    "23": [
        "{\"type\": \"read\", \"url\": \"/api/v1/orderOtherService/orderOther\", \"body\": \"{\\\"id\\\":\\\"76848992-e26e-4168-8c0e-30ce2a32354a\\\",\\\"boughtDate\\\":\\\"2024-05-09 18:31:54\\\",\\\"travelDate\\\":\\\"2024-05-09\\\",\\\"travelTime\\\":\\\"2013-05-04 09:51:52\\\",\\\"accountId\\\":\\\"4d2a46c7-71cb-4cf1-b5bb-b68406d9da6f\\\",\\\"contactsName\\\":\\\"Contacts_One\\\",\\\"documentType\\\":1,\\\"contactsDocumentNumber\\\":\\\"DocumentNumber_One\\\",\\\"trainNumber\\\":\\\"Z1234\\\",\\\"coachNumber\\\":5,\\\"seatClass\\\":2,\\\"seatNumber\\\":\\\"145098254\\\",\\\"from\\\":\\\"shanghai\\\",\\\"to\\\":\\\"nanjing\\\",\\\"status\\\":0,\\\"price\\\":\\\"350.0\\\",\\\"differenceMoney\\\":\\\"0.0\\\"}\", \"method\": \"POST\"}",
        "{\"type\": \"write\", \"url\": \"/api/v1/inside_pay_service/inside_payment/drawback/?/?\", \"body\": \"\", \"method\": \"GET\"}"
    ],
    "24": [
        "{\"type\": \"read\", \"url\": \"/api/v1/orderOtherService/orderOther\", \"body\": \"{\\\"id\\\":\\\"76848992-e26e-4168-8c0e-30ce2a32354a\\\",\\\"boughtDate\\\":\\\"2024-05-09 18:31:54\\\",\\\"travelDate\\\":\\\"2024-05-09\\\",\\\"travelTime\\\":\\\"2013-05-04 09:51:52\\\",\\\"accountId\\\":\\\"4d2a46c7-71cb-4cf1-b5bb-b68406d9da6f\\\",\\\"contactsName\\\":\\\"Contacts_One\\\",\\\"documentType\\\":1,\\\"contactsDocumentNumber\\\":\\\"DocumentNumber_One\\\",\\\"trainNumber\\\":\\\"Z1234\\\",\\\"coachNumber\\\":5,\\\"seatClass\\\":2,\\\"seatNumber\\\":\\\"145098254\\\",\\\"from\\\":\\\"shanghai\\\",\\\"to\\\":\\\"nanjing\\\",\\\"status\\\":0,\\\"price\\\":\\\"350.0\\\",\\\"differenceMoney\\\":\\\"0.0\\\"}\", \"method\": \"POST\"}",
        "{\"type\": \"write\", \"url\": \"/api/v1/orderOtherService/orderOther/status/?/?\", \"body\": \"\", \"method\": \"GET\"}"
    ],
    "25": [
        "{\"type\": \"write\", \"url\": \"/api/v1/orderOtherService/orderOther\", \"body\": \"{\\\"id\\\":\\\"76848992-e26e-4168-8c0e-30ce2a32354a\\\",\\\"boughtDate\\\":\\\"2024-05-09 18:31:54\\\",\\\"travelDate\\\":\\\"2024-05-09\\\",\\\"travelTime\\\":\\\"2013-05-04 09:51:52\\\",\\\"accountId\\\":\\\"4d2a46c7-71cb-4cf1-b5bb-b68406d9da6f\\\",\\\"contactsName\\\":\\\"Contacts_One\\\",\\\"documentType\\\":1,\\\"contactsDocumentNumber\\\":\\\"DocumentNumber_One\\\",\\\"trainNumber\\\":\\\"Z1234\\\",\\\"coachNumber\\\":5,\\\"seatClass\\\":2,\\\"seatNumber\\\":\\\"145098254\\\",\\\"from\\\":\\\"shanghai\\\",\\\"to\\\":\\\"nanjing\\\",\\\"status\\\":0,\\\"price\\\":\\\"350.0\\\",\\\"differenceMoney\\\":\\\"0.0\\\"}\", \"method\": \"POST\"}",
        "{\"type\": \"read\", \"url\": \"/api/v1/userservice/users/id/?\", \"body\": \"\", \"method\": \"GET\"}"
    ],
    "26": [
        "{\"type\": \"write\", \"url\": \"/api/v1/orderOtherService/orderOther\", \"body\": \"{\\\"id\\\":\\\"76848992-e26e-4168-8c0e-30ce2a32354a\\\",\\\"boughtDate\\\":\\\"2024-05-09 18:31:54\\\",\\\"travelDate\\\":\\\"2024-05-09\\\",\\\"travelTime\\\":\\\"2013-05-04 09:51:52\\\",\\\"accountId\\\":\\\"4d2a46c7-71cb-4cf1-b5bb-b68406d9da6f\\\",\\\"contactsName\\\":\\\"Contacts_One\\\",\\\"documentType\\\":1,\\\"contactsDocumentNumber\\\":\\\"DocumentNumber_One\\\",\\\"trainNumber\\\":\\\"Z1234\\\",\\\"coachNumber\\\":5,\\\"seatClass\\\":2,\\\"seatNumber\\\":\\\"145098254\\\",\\\"from\\\":\\\"shanghai\\\",\\\"to\\\":\\\"nanjing\\\",\\\"status\\\":0,\\\"price\\\":\\\"350.0\\\",\\\"differenceMoney\\\":\\\"0.0\\\"}\", \"method\": \"POST\"}",
        "{\"type\": \"read\", \"url\": \"/api/v1/orderOtherService/orderOther\", \"body\": \"{\\\"id\\\":\\\"0909b313-eeab-4463-a068-82f33d56cb49\\\",\\\"boughtDate\\\":\\\"2024-05-09 18:31:54\\\",\\\"travelDate\\\":\\\"2024-05-09\\\",\\\"travelTime\\\":\\\"2013-05-04 09:51:52\\\",\\\"accountId\\\":\\\"4d2a46c7-71cb-4cf1-b5bb-b68406d9da6f\\\",\\\"contactsName\\\":\\\"Contacts_One\\\",\\\"documentType\\\":1,\\\"contactsDocumentNumber\\\":\\\"DocumentNumber_One\\\",\\\"trainNumber\\\":\\\"Z1234\\\",\\\"coachNumber\\\":5,\\\"seatClass\\\":2,\\\"seatNumber\\\":\\\"145098254\\\",\\\"from\\\":\\\"shanghai\\\",\\\"to\\\":\\\"nanjing\\\",\\\"status\\\":4,\\\"price\\\":\\\"350.0\\\",\\\"differenceMoney\\\":\\\"0.0\\\"}\", \"method\": \"PUT\"}"
    ],
    "27": [
        "{\"type\": \"write\", \"url\": \"/api/v1/orderOtherService/orderOther\", \"body\": \"{\\\"id\\\":\\\"76848992-e26e-4168-8c0e-30ce2a32354a\\\",\\\"boughtDate\\\":\\\"2024-05-09 18:31:54\\\",\\\"travelDate\\\":\\\"2024-05-09\\\",\\\"travelTime\\\":\\\"2013-05-04 09:51:52\\\",\\\"accountId\\\":\\\"4d2a46c7-71cb-4cf1-b5bb-b68406d9da6f\\\",\\\"contactsName\\\":\\\"Contacts_One\\\",\\\"documentType\\\":1,\\\"contactsDocumentNumber\\\":\\\"DocumentNumber_One\\\",\\\"trainNumber\\\":\\\"Z1234\\\",\\\"coachNumber\\\":5,\\\"seatClass\\\":2,\\\"seatNumber\\\":\\\"145098254\\\",\\\"from\\\":\\\"shanghai\\\",\\\"to\\\":\\\"nanjing\\\",\\\"status\\\":0,\\\"price\\\":\\\"350.0\\\",\\\"differenceMoney\\\":\\\"0.0\\\"}\", \"method\": \"POST\"}",
        "{\"type\": \"read\", \"url\": \"/api/v1/orderOtherService/orderOther/?\", \"body\": \"\", \"method\": \"GET\"}"
    ],
    "28": [
        "{\"type\": \"write\", \"url\": \"/api/v1/orderOtherService/orderOther\", \"body\": \"{\\\"id\\\":\\\"76848992-e26e-4168-8c0e-30ce2a32354a\\\",\\\"boughtDate\\\":\\\"2024-05-09 18:31:54\\\",\\\"travelDate\\\":\\\"2024-05-09\\\",\\\"travelTime\\\":\\\"2013-05-04 09:51:52\\\",\\\"accountId\\\":\\\"4d2a46c7-71cb-4cf1-b5bb-b68406d9da6f\\\",\\\"contactsName\\\":\\\"Contacts_One\\\",\\\"documentType\\\":1,\\\"contactsDocumentNumber\\\":\\\"DocumentNumber_One\\\",\\\"trainNumber\\\":\\\"Z1234\\\",\\\"coachNumber\\\":5,\\\"seatClass\\\":2,\\\"seatNumber\\\":\\\"145098254\\\",\\\"from\\\":\\\"shanghai\\\",\\\"to\\\":\\\"nanjing\\\",\\\"status\\\":0,\\\"price\\\":\\\"350.0\\\",\\\"differenceMoney\\\":\\\"0.0\\\"}\", \"method\": \"POST\"}",
        "{\"type\": \"read\", \"url\": \"/api/v1/orderOtherService/orderOther\", \"body\": \"{\\\"id\\\":\\\"0909b313-eeab-4463-a068-82f33d56cb49\\\",\\\"boughtDate\\\":\\\"2024-05-09 18:31:54\\\",\\\"travelDate\\\":\\\"2024-05-09\\\",\\\"travelTime\\\":\\\"2013-05-04 09:51:52\\\",\\\"accountId\\\":\\\"4d2a46c7-71cb-4cf1-b5bb-b68406d9da6f\\\",\\\"contactsName\\\":\\\"Contacts_One\\\",\\\"documentType\\\":1,\\\"contactsDocumentNumber\\\":\\\"DocumentNumber_One\\\",\\\"trainNumber\\\":\\\"Z1234\\\",\\\"coachNumber\\\":5,\\\"seatClass\\\":2,\\\"seatNumber\\\":\\\"145098254\\\",\\\"from\\\":\\\"shanghai\\\",\\\"to\\\":\\\"nanjing\\\",\\\"status\\\":7,\\\"price\\\":\\\"350.0\\\",\\\"differenceMoney\\\":\\\"0.0\\\"}\", \"method\": \"PUT\"}"
    ],
    "29": [
        "{\"type\": \"write\", \"url\": \"/api/v1/orderOtherService/orderOther\", \"body\": \"{\\\"id\\\":\\\"76848992-e26e-4168-8c0e-30ce2a32354a\\\",\\\"boughtDate\\\":\\\"2024-05-09 18:31:54\\\",\\\"travelDate\\\":\\\"2024-05-09\\\",\\\"travelTime\\\":\\\"2013-05-04 09:51:52\\\",\\\"accountId\\\":\\\"4d2a46c7-71cb-4cf1-b5bb-b68406d9da6f\\\",\\\"contactsName\\\":\\\"Contacts_One\\\",\\\"documentType\\\":1,\\\"contactsDocumentNumber\\\":\\\"DocumentNumber_One\\\",\\\"trainNumber\\\":\\\"Z1234\\\",\\\"coachNumber\\\":5,\\\"seatClass\\\":2,\\\"seatNumber\\\":\\\"145098254\\\",\\\"from\\\":\\\"shanghai\\\",\\\"to\\\":\\\"nanjing\\\",\\\"status\\\":0,\\\"price\\\":\\\"350.0\\\",\\\"differenceMoney\\\":\\\"0.0\\\"}\", \"method\": \"POST\"}",
        "{\"type\": \"read\", \"url\": \"/api/v1/inside_pay_service/inside_payment/drawback/?/?\", \"body\": \"\", \"method\": \"GET\"}"
    ],
    "30": [
        "{\"type\": \"write\", \"url\": \"/api/v1/orderOtherService/orderOther\", \"body\": \"{\\\"id\\\":\\\"76848992-e26e-4168-8c0e-30ce2a32354a\\\",\\\"boughtDate\\\":\\\"2024-05-09 18:31:54\\\",\\\"travelDate\\\":\\\"2024-05-09\\\",\\\"travelTime\\\":\\\"2013-05-04 09:51:52\\\",\\\"accountId\\\":\\\"4d2a46c7-71cb-4cf1-b5bb-b68406d9da6f\\\",\\\"contactsName\\\":\\\"Contacts_One\\\",\\\"documentType\\\":1,\\\"contactsDocumentNumber\\\":\\\"DocumentNumber_One\\\",\\\"trainNumber\\\":\\\"Z1234\\\",\\\"coachNumber\\\":5,\\\"seatClass\\\":2,\\\"seatNumber\\\":\\\"145098254\\\",\\\"from\\\":\\\"shanghai\\\",\\\"to\\\":\\\"nanjing\\\",\\\"status\\\":0,\\\"price\\\":\\\"350.0\\\",\\\"differenceMoney\\\":\\\"0.0\\\"}\", \"method\": \"POST\"}",
        "{\"type\": \"write\", \"url\": \"/api/v1/inside_pay_service/inside_payment/drawback/?/?\", \"body\": \"\", \"method\": \"GET\"}"
    ],
    "31": [
        "{\"type\": \"write\", \"url\": \"/api/v1/orderOtherService/orderOther\", \"body\": \"{\\\"id\\\":\\\"76848992-e26e-4168-8c0e-30ce2a32354a\\\",\\\"boughtDate\\\":\\\"2024-05-09 18:31:54\\\",\\\"travelDate\\\":\\\"2024-05-09\\\",\\\"travelTime\\\":\\\"2013-05-04 09:51:52\\\",\\\"accountId\\\":\\\"4d2a46c7-71cb-4cf1-b5bb-b68406d9da6f\\\",\\\"contactsName\\\":\\\"Contacts_One\\\",\\\"documentType\\\":1,\\\"contactsDocumentNumber\\\":\\\"DocumentNumber_One\\\",\\\"trainNumber\\\":\\\"Z1234\\\",\\\"coachNumber\\\":5,\\\"seatClass\\\":2,\\\"seatNumber\\\":\\\"145098254\\\",\\\"from\\\":\\\"shanghai\\\",\\\"to\\\":\\\"nanjing\\\",\\\"status\\\":0,\\\"price\\\":\\\"350.0\\\",\\\"differenceMoney\\\":\\\"0.0\\\"}\", \"method\": \"POST\"}",
        "{\"type\": \"read\", \"url\": \"/api/v1/orderservice/order/?\", \"body\": \"\", \"method\": \"GET\"}"
    ],
    "32": [
        "{\"type\": \"write\", \"url\": \"/api/v1/orderOtherService/orderOther\", \"body\": \"{\\\"id\\\":\\\"76848992-e26e-4168-8c0e-30ce2a32354a\\\",\\\"boughtDate\\\":\\\"2024-05-09 18:31:54\\\",\\\"travelDate\\\":\\\"2024-05-09\\\",\\\"travelTime\\\":\\\"2013-05-04 09:51:52\\\",\\\"accountId\\\":\\\"4d2a46c7-71cb-4cf1-b5bb-b68406d9da6f\\\",\\\"contactsName\\\":\\\"Contacts_One\\\",\\\"documentType\\\":1,\\\"contactsDocumentNumber\\\":\\\"DocumentNumber_One\\\",\\\"trainNumber\\\":\\\"Z1234\\\",\\\"coachNumber\\\":5,\\\"seatClass\\\":2,\\\"seatNumber\\\":\\\"145098254\\\",\\\"from\\\":\\\"shanghai\\\",\\\"to\\\":\\\"nanjing\\\",\\\"status\\\":0,\\\"price\\\":\\\"350.0\\\",\\\"differenceMoney\\\":\\\"0.0\\\"}\", \"method\": \"POST\"}",
        "{\"type\": \"read\", \"url\": \"/api/v1/orderOtherService/orderOther/?\", \"body\": \"\", \"method\": \"GET\"}"
    ],
    "33": [
        "{\"type\": \"write\", \"url\": \"/api/v1/orderOtherService/orderOther\", \"body\": \"{\\\"id\\\":\\\"76848992-e26e-4168-8c0e-30ce2a32354a\\\",\\\"boughtDate\\\":\\\"2024-05-09 18:31:54\\\",\\\"travelDate\\\":\\\"2024-05-09\\\",\\\"travelTime\\\":\\\"2013-05-04 09:51:52\\\",\\\"accountId\\\":\\\"4d2a46c7-71cb-4cf1-b5bb-b68406d9da6f\\\",\\\"contactsName\\\":\\\"Contacts_One\\\",\\\"documentType\\\":1,\\\"contactsDocumentNumber\\\":\\\"DocumentNumber_One\\\",\\\"trainNumber\\\":\\\"Z1234\\\",\\\"coachNumber\\\":5,\\\"seatClass\\\":2,\\\"seatNumber\\\":\\\"145098254\\\",\\\"from\\\":\\\"shanghai\\\",\\\"to\\\":\\\"nanjing\\\",\\\"status\\\":0,\\\"price\\\":\\\"350.0\\\",\\\"differenceMoney\\\":\\\"0.0\\\"}\", \"method\": \"POST\"}",
        "{\"type\": \"read\", \"url\": \"/api/v1/orderOtherService/orderOther/?\", \"body\": \"\", \"method\": \"GET\"}"
    ],
    "34": [
        "{\"type\": \"write\", \"url\": \"/api/v1/orderOtherService/orderOther\", \"body\": \"{\\\"id\\\":\\\"76848992-e26e-4168-8c0e-30ce2a32354a\\\",\\\"boughtDate\\\":\\\"2024-05-09 18:31:54\\\",\\\"travelDate\\\":\\\"2024-05-09\\\",\\\"travelTime\\\":\\\"2013-05-04 09:51:52\\\",\\\"accountId\\\":\\\"4d2a46c7-71cb-4cf1-b5bb-b68406d9da6f\\\",\\\"contactsName\\\":\\\"Contacts_One\\\",\\\"documentType\\\":1,\\\"contactsDocumentNumber\\\":\\\"DocumentNumber_One\\\",\\\"trainNumber\\\":\\\"Z1234\\\",\\\"coachNumber\\\":5,\\\"seatClass\\\":2,\\\"seatNumber\\\":\\\"145098254\\\",\\\"from\\\":\\\"shanghai\\\",\\\"to\\\":\\\"nanjing\\\",\\\"status\\\":0,\\\"price\\\":\\\"350.0\\\",\\\"differenceMoney\\\":\\\"0.0\\\"}\", \"method\": \"POST\"}",
        "{\"type\": \"read\", \"url\": \"/api/v1/orderOtherService/orderOther/?\", \"body\": \"\", \"method\": \"GET\"}"
    ],
    "35": [
        "{\"type\": \"write\", \"url\": \"/api/v1/orderOtherService/orderOther\", \"body\": \"{\\\"id\\\":\\\"76848992-e26e-4168-8c0e-30ce2a32354a\\\",\\\"boughtDate\\\":\\\"2024-05-09 18:31:54\\\",\\\"travelDate\\\":\\\"2024-05-09\\\",\\\"travelTime\\\":\\\"2013-05-04 09:51:52\\\",\\\"accountId\\\":\\\"4d2a46c7-71cb-4cf1-b5bb-b68406d9da6f\\\",\\\"contactsName\\\":\\\"Contacts_One\\\",\\\"documentType\\\":1,\\\"contactsDocumentNumber\\\":\\\"DocumentNumber_One\\\",\\\"trainNumber\\\":\\\"Z1234\\\",\\\"coachNumber\\\":5,\\\"seatClass\\\":2,\\\"seatNumber\\\":\\\"145098254\\\",\\\"from\\\":\\\"shanghai\\\",\\\"to\\\":\\\"nanjing\\\",\\\"status\\\":0,\\\"price\\\":\\\"350.0\\\",\\\"differenceMoney\\\":\\\"0.0\\\"}\", \"method\": \"POST\"}",
        "{\"type\": \"read\", \"url\": \"/api/v1/paymentservice/payment\", \"body\": \"{\\\"id\\\":null,\\\"orderId\\\":\\\"0909b313-eeab-4463-a068-82f33d56cb49\\\",\\\"userId\\\":null,\\\"price\\\":\\\"350.0\\\",\\\"type\\\":null}\", \"method\": \"POST\"}"
    ],
    "36": [
        "{\"type\": \"write\", \"url\": \"/api/v1/orderOtherService/orderOther\", \"body\": \"{\\\"id\\\":\\\"76848992-e26e-4168-8c0e-30ce2a32354a\\\",\\\"boughtDate\\\":\\\"2024-05-09 18:31:54\\\",\\\"travelDate\\\":\\\"2024-05-09\\\",\\\"travelTime\\\":\\\"2013-05-04 09:51:52\\\",\\\"accountId\\\":\\\"4d2a46c7-71cb-4cf1-b5bb-b68406d9da6f\\\",\\\"contactsName\\\":\\\"Contacts_One\\\",\\\"documentType\\\":1,\\\"contactsDocumentNumber\\\":\\\"DocumentNumber_One\\\",\\\"trainNumber\\\":\\\"Z1234\\\",\\\"coachNumber\\\":5,\\\"seatClass\\\":2,\\\"seatNumber\\\":\\\"145098254\\\",\\\"from\\\":\\\"shanghai\\\",\\\"to\\\":\\\"nanjing\\\",\\\"status\\\":0,\\\"price\\\":\\\"350.0\\\",\\\"differenceMoney\\\":\\\"0.0\\\"}\", \"method\": \"POST\"}",
        "{\"type\": \"write\", \"url\": \"/api/v1/paymentservice/payment\", \"body\": \"{\\\"id\\\":null,\\\"orderId\\\":\\\"0909b313-eeab-4463-a068-82f33d56cb49\\\",\\\"userId\\\":null,\\\"price\\\":\\\"350.0\\\",\\\"type\\\":null}\", \"method\": \"POST\"}"
    ],
    "37": [
        "{\"type\": \"write\", \"url\": \"/api/v1/orderOtherService/orderOther\", \"body\": \"{\\\"id\\\":\\\"76848992-e26e-4168-8c0e-30ce2a32354a\\\",\\\"boughtDate\\\":\\\"2024-05-09 18:31:54\\\",\\\"travelDate\\\":\\\"2024-05-09\\\",\\\"travelTime\\\":\\\"2013-05-04 09:51:52\\\",\\\"accountId\\\":\\\"4d2a46c7-71cb-4cf1-b5bb-b68406d9da6f\\\",\\\"contactsName\\\":\\\"Contacts_One\\\",\\\"documentType\\\":1,\\\"contactsDocumentNumber\\\":\\\"DocumentNumber_One\\\",\\\"trainNumber\\\":\\\"Z1234\\\",\\\"coachNumber\\\":5,\\\"seatClass\\\":2,\\\"seatNumber\\\":\\\"145098254\\\",\\\"from\\\":\\\"shanghai\\\",\\\"to\\\":\\\"nanjing\\\",\\\"status\\\":0,\\\"price\\\":\\\"350.0\\\",\\\"differenceMoney\\\":\\\"0.0\\\"}\", \"method\": \"POST\"}",
        "{\"type\": \"write\", \"url\": \"/api/v1/inside_pay_service/inside_payment\", \"body\": \"\", \"method\": \"POST\"}"
    ],
    "38": [
        "{\"type\": \"write\", \"url\": \"/api/v1/orderOtherService/orderOther\", \"body\": \"{\\\"id\\\":\\\"76848992-e26e-4168-8c0e-30ce2a32354a\\\",\\\"boughtDate\\\":\\\"2024-05-09 18:31:54\\\",\\\"travelDate\\\":\\\"2024-05-09\\\",\\\"travelTime\\\":\\\"2013-05-04 09:51:52\\\",\\\"accountId\\\":\\\"4d2a46c7-71cb-4cf1-b5bb-b68406d9da6f\\\",\\\"contactsName\\\":\\\"Contacts_One\\\",\\\"documentType\\\":1,\\\"contactsDocumentNumber\\\":\\\"DocumentNumber_One\\\",\\\"trainNumber\\\":\\\"Z1234\\\",\\\"coachNumber\\\":5,\\\"seatClass\\\":2,\\\"seatNumber\\\":\\\"145098254\\\",\\\"from\\\":\\\"shanghai\\\",\\\"to\\\":\\\"nanjing\\\",\\\"status\\\":0,\\\"price\\\":\\\"350.0\\\",\\\"differenceMoney\\\":\\\"0.0\\\"}\", \"method\": \"POST\"}",
        "{\"type\": \"read\", \"url\": \"/api/v1/orderOtherService/orderOther/status/?/?\", \"body\": \"\", \"method\": \"GET\"}"
    ],
    "39": [
        "{\"type\": \"read\", \"url\": \"/api/v1/userservice/users/id/?\", \"body\": \"\", \"method\": \"GET\"}",
        "{\"type\": \"write\", \"url\": \"/api/v1/orderOtherService/orderOther\", \"body\": \"{\\\"id\\\":\\\"0909b313-eeab-4463-a068-82f33d56cb49\\\",\\\"boughtDate\\\":\\\"2024-05-09 18:31:54\\\",\\\"travelDate\\\":\\\"2024-05-09\\\",\\\"travelTime\\\":\\\"2013-05-04 09:51:52\\\",\\\"accountId\\\":\\\"4d2a46c7-71cb-4cf1-b5bb-b68406d9da6f\\\",\\\"contactsName\\\":\\\"Contacts_One\\\",\\\"documentType\\\":1,\\\"contactsDocumentNumber\\\":\\\"DocumentNumber_One\\\",\\\"trainNumber\\\":\\\"Z1234\\\",\\\"coachNumber\\\":5,\\\"seatClass\\\":2,\\\"seatNumber\\\":\\\"145098254\\\",\\\"from\\\":\\\"shanghai\\\",\\\"to\\\":\\\"nanjing\\\",\\\"status\\\":4,\\\"price\\\":\\\"350.0\\\",\\\"differenceMoney\\\":\\\"0.0\\\"}\", \"method\": \"PUT\"}"
    ],
    "40": [
        "{\"type\": \"read\", \"url\": \"/api/v1/userservice/users/id/?\", \"body\": \"\", \"method\": \"GET\"}",
        "{\"type\": \"write\", \"url\": \"/api/v1/orderOtherService/orderOther\", \"body\": \"{\\\"id\\\":\\\"0909b313-eeab-4463-a068-82f33d56cb49\\\",\\\"boughtDate\\\":\\\"2024-05-09 18:31:54\\\",\\\"travelDate\\\":\\\"2024-05-09\\\",\\\"travelTime\\\":\\\"2013-05-04 09:51:52\\\",\\\"accountId\\\":\\\"4d2a46c7-71cb-4cf1-b5bb-b68406d9da6f\\\",\\\"contactsName\\\":\\\"Contacts_One\\\",\\\"documentType\\\":1,\\\"contactsDocumentNumber\\\":\\\"DocumentNumber_One\\\",\\\"trainNumber\\\":\\\"Z1234\\\",\\\"coachNumber\\\":5,\\\"seatClass\\\":2,\\\"seatNumber\\\":\\\"145098254\\\",\\\"from\\\":\\\"shanghai\\\",\\\"to\\\":\\\"nanjing\\\",\\\"status\\\":7,\\\"price\\\":\\\"350.0\\\",\\\"differenceMoney\\\":\\\"0.0\\\"}\", \"method\": \"PUT\"}"
    ],
    "41": [
        "{\"type\": \"read\", \"url\": \"/api/v1/userservice/users/id/?\", \"body\": \"\", \"method\": \"GET\"}",
        "{\"type\": \"write\", \"url\": \"/api/v1/inside_pay_service/inside_payment/drawback/?/?\", \"body\": \"\", \"method\": \"GET\"}"
    ],
    "42": [
        "{\"type\": \"read\", \"url\": \"/api/v1/userservice/users/id/?\", \"body\": \"\", \"method\": \"GET\"}",
        "{\"type\": \"write\", \"url\": \"/api/v1/orderOtherService/orderOther/status/?/?\", \"body\": \"\", \"method\": \"GET\"}"
    ],
    "43": [
        "{\"type\": \"read\", \"url\": \"/api/v1/orderOtherService/orderOther\", \"body\": \"{\\\"id\\\":\\\"0909b313-eeab-4463-a068-82f33d56cb49\\\",\\\"boughtDate\\\":\\\"2024-05-09 18:31:54\\\",\\\"travelDate\\\":\\\"2024-05-09\\\",\\\"travelTime\\\":\\\"2013-05-04 09:51:52\\\",\\\"accountId\\\":\\\"4d2a46c7-71cb-4cf1-b5bb-b68406d9da6f\\\",\\\"contactsName\\\":\\\"Contacts_One\\\",\\\"documentType\\\":1,\\\"contactsDocumentNumber\\\":\\\"DocumentNumber_One\\\",\\\"trainNumber\\\":\\\"Z1234\\\",\\\"coachNumber\\\":5,\\\"seatClass\\\":2,\\\"seatNumber\\\":\\\"145098254\\\",\\\"from\\\":\\\"shanghai\\\",\\\"to\\\":\\\"nanjing\\\",\\\"status\\\":4,\\\"price\\\":\\\"350.0\\\",\\\"differenceMoney\\\":\\\"0.0\\\"}\", \"method\": \"PUT\"}",
        "{\"type\": \"write\", \"url\": \"/api/v1/orderOtherService/orderOther\", \"body\": \"{\\\"id\\\":\\\"0909b313-eeab-4463-a068-82f33d56cb49\\\",\\\"boughtDate\\\":\\\"2024-05-09 18:31:54\\\",\\\"travelDate\\\":\\\"2024-05-09\\\",\\\"travelTime\\\":\\\"2013-05-04 09:51:52\\\",\\\"accountId\\\":\\\"4d2a46c7-71cb-4cf1-b5bb-b68406d9da6f\\\",\\\"contactsName\\\":\\\"Contacts_One\\\",\\\"documentType\\\":1,\\\"contactsDocumentNumber\\\":\\\"DocumentNumber_One\\\",\\\"trainNumber\\\":\\\"Z1234\\\",\\\"coachNumber\\\":5,\\\"seatClass\\\":2,\\\"seatNumber\\\":\\\"145098254\\\",\\\"from\\\":\\\"shanghai\\\",\\\"to\\\":\\\"nanjing\\\",\\\"status\\\":7,\\\"price\\\":\\\"350.0\\\",\\\"differenceMoney\\\":\\\"0.0\\\"}\", \"method\": \"PUT\"}"
    ],
    "44": [
        "{\"type\": \"read\", \"url\": \"/api/v1/orderOtherService/orderOther\", \"body\": \"{\\\"id\\\":\\\"0909b313-eeab-4463-a068-82f33d56cb49\\\",\\\"boughtDate\\\":\\\"2024-05-09 18:31:54\\\",\\\"travelDate\\\":\\\"2024-05-09\\\",\\\"travelTime\\\":\\\"2013-05-04 09:51:52\\\",\\\"accountId\\\":\\\"4d2a46c7-71cb-4cf1-b5bb-b68406d9da6f\\\",\\\"contactsName\\\":\\\"Contacts_One\\\",\\\"documentType\\\":1,\\\"contactsDocumentNumber\\\":\\\"DocumentNumber_One\\\",\\\"trainNumber\\\":\\\"Z1234\\\",\\\"coachNumber\\\":5,\\\"seatClass\\\":2,\\\"seatNumber\\\":\\\"145098254\\\",\\\"from\\\":\\\"shanghai\\\",\\\"to\\\":\\\"nanjing\\\",\\\"status\\\":4,\\\"price\\\":\\\"350.0\\\",\\\"differenceMoney\\\":\\\"0.0\\\"}\", \"method\": \"PUT\"}",
        "{\"type\": \"write\", \"url\": \"/api/v1/paymentservice/payment\", \"body\": \"{\\\"id\\\":null,\\\"orderId\\\":\\\"0909b313-eeab-4463-a068-82f33d56cb49\\\",\\\"userId\\\":null,\\\"price\\\":\\\"350.0\\\",\\\"type\\\":null}\", \"method\": \"POST\"}"
    ],
    "45": [
        "{\"type\": \"read\", \"url\": \"/api/v1/orderOtherService/orderOther\", \"body\": \"{\\\"id\\\":\\\"0909b313-eeab-4463-a068-82f33d56cb49\\\",\\\"boughtDate\\\":\\\"2024-05-09 18:31:54\\\",\\\"travelDate\\\":\\\"2024-05-09\\\",\\\"travelTime\\\":\\\"2013-05-04 09:51:52\\\",\\\"accountId\\\":\\\"4d2a46c7-71cb-4cf1-b5bb-b68406d9da6f\\\",\\\"contactsName\\\":\\\"Contacts_One\\\",\\\"documentType\\\":1,\\\"contactsDocumentNumber\\\":\\\"DocumentNumber_One\\\",\\\"trainNumber\\\":\\\"Z1234\\\",\\\"coachNumber\\\":5,\\\"seatClass\\\":2,\\\"seatNumber\\\":\\\"145098254\\\",\\\"from\\\":\\\"shanghai\\\",\\\"to\\\":\\\"nanjing\\\",\\\"status\\\":4,\\\"price\\\":\\\"350.0\\\",\\\"differenceMoney\\\":\\\"0.0\\\"}\", \"method\": \"PUT\"}",
        "{\"type\": \"write\", \"url\": \"/api/v1/inside_pay_service/inside_payment\", \"body\": \"\", \"method\": \"POST\"}"
    ],
    "46": [
        "{\"type\": \"read\", \"url\": \"/api/v1/orderOtherService/orderOther\", \"body\": \"{\\\"id\\\":\\\"0909b313-eeab-4463-a068-82f33d56cb49\\\",\\\"boughtDate\\\":\\\"2024-05-09 18:31:54\\\",\\\"travelDate\\\":\\\"2024-05-09\\\",\\\"travelTime\\\":\\\"2013-05-04 09:51:52\\\",\\\"accountId\\\":\\\"4d2a46c7-71cb-4cf1-b5bb-b68406d9da6f\\\",\\\"contactsName\\\":\\\"Contacts_One\\\",\\\"documentType\\\":1,\\\"contactsDocumentNumber\\\":\\\"DocumentNumber_One\\\",\\\"trainNumber\\\":\\\"Z1234\\\",\\\"coachNumber\\\":5,\\\"seatClass\\\":2,\\\"seatNumber\\\":\\\"145098254\\\",\\\"from\\\":\\\"shanghai\\\",\\\"to\\\":\\\"nanjing\\\",\\\"status\\\":4,\\\"price\\\":\\\"350.0\\\",\\\"differenceMoney\\\":\\\"0.0\\\"}\", \"method\": \"PUT\"}",
        "{\"type\": \"write\", \"url\": \"/api/v1/orderOtherService/orderOther/status/?/?\", \"body\": \"\", \"method\": \"GET\"}"
    ],
    "47": [
        "{\"type\": \"write\", \"url\": \"/api/v1/orderOtherService/orderOther\", \"body\": \"{\\\"id\\\":\\\"0909b313-eeab-4463-a068-82f33d56cb49\\\",\\\"boughtDate\\\":\\\"2024-05-09 18:31:54\\\",\\\"travelDate\\\":\\\"2024-05-09\\\",\\\"travelTime\\\":\\\"2013-05-04 09:51:52\\\",\\\"accountId\\\":\\\"4d2a46c7-71cb-4cf1-b5bb-b68406d9da6f\\\",\\\"contactsName\\\":\\\"Contacts_One\\\",\\\"documentType\\\":1,\\\"contactsDocumentNumber\\\":\\\"DocumentNumber_One\\\",\\\"trainNumber\\\":\\\"Z1234\\\",\\\"coachNumber\\\":5,\\\"seatClass\\\":2,\\\"seatNumber\\\":\\\"145098254\\\",\\\"from\\\":\\\"shanghai\\\",\\\"to\\\":\\\"nanjing\\\",\\\"status\\\":4,\\\"price\\\":\\\"350.0\\\",\\\"differenceMoney\\\":\\\"0.0\\\"}\", \"method\": \"PUT\"}",
        "{\"type\": \"read\", \"url\": \"/api/v1/orderOtherService/orderOther/?\", \"body\": \"\", \"method\": \"GET\"}"
    ],
    "48": [
        "{\"type\": \"write\", \"url\": \"/api/v1/orderOtherService/orderOther\", \"body\": \"{\\\"id\\\":\\\"0909b313-eeab-4463-a068-82f33d56cb49\\\",\\\"boughtDate\\\":\\\"2024-05-09 18:31:54\\\",\\\"travelDate\\\":\\\"2024-05-09\\\",\\\"travelTime\\\":\\\"2013-05-04 09:51:52\\\",\\\"accountId\\\":\\\"4d2a46c7-71cb-4cf1-b5bb-b68406d9da6f\\\",\\\"contactsName\\\":\\\"Contacts_One\\\",\\\"documentType\\\":1,\\\"contactsDocumentNumber\\\":\\\"DocumentNumber_One\\\",\\\"trainNumber\\\":\\\"Z1234\\\",\\\"coachNumber\\\":5,\\\"seatClass\\\":2,\\\"seatNumber\\\":\\\"145098254\\\",\\\"from\\\":\\\"shanghai\\\",\\\"to\\\":\\\"nanjing\\\",\\\"status\\\":4,\\\"price\\\":\\\"350.0\\\",\\\"differenceMoney\\\":\\\"0.0\\\"}\", \"method\": \"PUT\"}",
        "{\"type\": \"read\", \"url\": \"/api/v1/orderOtherService/orderOther\", \"body\": \"{\\\"id\\\":\\\"0909b313-eeab-4463-a068-82f33d56cb49\\\",\\\"boughtDate\\\":\\\"2024-05-09 18:31:54\\\",\\\"travelDate\\\":\\\"2024-05-09\\\",\\\"travelTime\\\":\\\"2013-05-04 09:51:52\\\",\\\"accountId\\\":\\\"4d2a46c7-71cb-4cf1-b5bb-b68406d9da6f\\\",\\\"contactsName\\\":\\\"Contacts_One\\\",\\\"documentType\\\":1,\\\"contactsDocumentNumber\\\":\\\"DocumentNumber_One\\\",\\\"trainNumber\\\":\\\"Z1234\\\",\\\"coachNumber\\\":5,\\\"seatClass\\\":2,\\\"seatNumber\\\":\\\"145098254\\\",\\\"from\\\":\\\"shanghai\\\",\\\"to\\\":\\\"nanjing\\\",\\\"status\\\":7,\\\"price\\\":\\\"350.0\\\",\\\"differenceMoney\\\":\\\"0.0\\\"}\", \"method\": \"PUT\"}"
    ],
    "49": [
        "{\"type\": \"write\", \"url\": \"/api/v1/orderOtherService/orderOther\", \"body\": \"{\\\"id\\\":\\\"0909b313-eeab-4463-a068-82f33d56cb49\\\",\\\"boughtDate\\\":\\\"2024-05-09 18:31:54\\\",\\\"travelDate\\\":\\\"2024-05-09\\\",\\\"travelTime\\\":\\\"2013-05-04 09:51:52\\\",\\\"accountId\\\":\\\"4d2a46c7-71cb-4cf1-b5bb-b68406d9da6f\\\",\\\"contactsName\\\":\\\"Contacts_One\\\",\\\"documentType\\\":1,\\\"contactsDocumentNumber\\\":\\\"DocumentNumber_One\\\",\\\"trainNumber\\\":\\\"Z1234\\\",\\\"coachNumber\\\":5,\\\"seatClass\\\":2,\\\"seatNumber\\\":\\\"145098254\\\",\\\"from\\\":\\\"shanghai\\\",\\\"to\\\":\\\"nanjing\\\",\\\"status\\\":4,\\\"price\\\":\\\"350.0\\\",\\\"differenceMoney\\\":\\\"0.0\\\"}\", \"method\": \"PUT\"}",
        "{\"type\": \"read\", \"url\": \"/api/v1/inside_pay_service/inside_payment/drawback/?/?\", \"body\": \"\", \"method\": \"GET\"}"
    ],
    "50": [
        "{\"type\": \"write\", \"url\": \"/api/v1/orderOtherService/orderOther\", \"body\": \"{\\\"id\\\":\\\"0909b313-eeab-4463-a068-82f33d56cb49\\\",\\\"boughtDate\\\":\\\"2024-05-09 18:31:54\\\",\\\"travelDate\\\":\\\"2024-05-09\\\",\\\"travelTime\\\":\\\"2013-05-04 09:51:52\\\",\\\"accountId\\\":\\\"4d2a46c7-71cb-4cf1-b5bb-b68406d9da6f\\\",\\\"contactsName\\\":\\\"Contacts_One\\\",\\\"documentType\\\":1,\\\"contactsDocumentNumber\\\":\\\"DocumentNumber_One\\\",\\\"trainNumber\\\":\\\"Z1234\\\",\\\"coachNumber\\\":5,\\\"seatClass\\\":2,\\\"seatNumber\\\":\\\"145098254\\\",\\\"from\\\":\\\"shanghai\\\",\\\"to\\\":\\\"nanjing\\\",\\\"status\\\":4,\\\"price\\\":\\\"350.0\\\",\\\"differenceMoney\\\":\\\"0.0\\\"}\", \"method\": \"PUT\"}",
        "{\"type\": \"write\", \"url\": \"/api/v1/inside_pay_service/inside_payment/drawback/?/?\", \"body\": \"\", \"method\": \"GET\"}"
    ],
    "51": [
        "{\"type\": \"write\", \"url\": \"/api/v1/orderOtherService/orderOther\", \"body\": \"{\\\"id\\\":\\\"0909b313-eeab-4463-a068-82f33d56cb49\\\",\\\"boughtDate\\\":\\\"2024-05-09 18:31:54\\\",\\\"travelDate\\\":\\\"2024-05-09\\\",\\\"travelTime\\\":\\\"2013-05-04 09:51:52\\\",\\\"accountId\\\":\\\"4d2a46c7-71cb-4cf1-b5bb-b68406d9da6f\\\",\\\"contactsName\\\":\\\"Contacts_One\\\",\\\"documentType\\\":1,\\\"contactsDocumentNumber\\\":\\\"DocumentNumber_One\\\",\\\"trainNumber\\\":\\\"Z1234\\\",\\\"coachNumber\\\":5,\\\"seatClass\\\":2,\\\"seatNumber\\\":\\\"145098254\\\",\\\"from\\\":\\\"shanghai\\\",\\\"to\\\":\\\"nanjing\\\",\\\"status\\\":4,\\\"price\\\":\\\"350.0\\\",\\\"differenceMoney\\\":\\\"0.0\\\"}\", \"method\": \"PUT\"}",
        "{\"type\": \"read\", \"url\": \"/api/v1/orderservice/order/?\", \"body\": \"\", \"method\": \"GET\"}"
    ],
    "52": [
        "{\"type\": \"write\", \"url\": \"/api/v1/orderOtherService/orderOther\", \"body\": \"{\\\"id\\\":\\\"0909b313-eeab-4463-a068-82f33d56cb49\\\",\\\"boughtDate\\\":\\\"2024-05-09 18:31:54\\\",\\\"travelDate\\\":\\\"2024-05-09\\\",\\\"travelTime\\\":\\\"2013-05-04 09:51:52\\\",\\\"accountId\\\":\\\"4d2a46c7-71cb-4cf1-b5bb-b68406d9da6f\\\",\\\"contactsName\\\":\\\"Contacts_One\\\",\\\"documentType\\\":1,\\\"contactsDocumentNumber\\\":\\\"DocumentNumber_One\\\",\\\"trainNumber\\\":\\\"Z1234\\\",\\\"coachNumber\\\":5,\\\"seatClass\\\":2,\\\"seatNumber\\\":\\\"145098254\\\",\\\"from\\\":\\\"shanghai\\\",\\\"to\\\":\\\"nanjing\\\",\\\"status\\\":4,\\\"price\\\":\\\"350.0\\\",\\\"differenceMoney\\\":\\\"0.0\\\"}\", \"method\": \"PUT\"}",
        "{\"type\": \"read\", \"url\": \"/api/v1/orderOtherService/orderOther/?\", \"body\": \"\", \"method\": \"GET\"}"
    ],
    "53": [
        "{\"type\": \"write\", \"url\": \"/api/v1/orderOtherService/orderOther\", \"body\": \"{\\\"id\\\":\\\"0909b313-eeab-4463-a068-82f33d56cb49\\\",\\\"boughtDate\\\":\\\"2024-05-09 18:31:54\\\",\\\"travelDate\\\":\\\"2024-05-09\\\",\\\"travelTime\\\":\\\"2013-05-04 09:51:52\\\",\\\"accountId\\\":\\\"4d2a46c7-71cb-4cf1-b5bb-b68406d9da6f\\\",\\\"contactsName\\\":\\\"Contacts_One\\\",\\\"documentType\\\":1,\\\"contactsDocumentNumber\\\":\\\"DocumentNumber_One\\\",\\\"trainNumber\\\":\\\"Z1234\\\",\\\"coachNumber\\\":5,\\\"seatClass\\\":2,\\\"seatNumber\\\":\\\"145098254\\\",\\\"from\\\":\\\"shanghai\\\",\\\"to\\\":\\\"nanjing\\\",\\\"status\\\":4,\\\"price\\\":\\\"350.0\\\",\\\"differenceMoney\\\":\\\"0.0\\\"}\", \"method\": \"PUT\"}",
        "{\"type\": \"read\", \"url\": \"/api/v1/orderOtherService/orderOther/?\", \"body\": \"\", \"method\": \"GET\"}"
    ],
    "54": [
        "{\"type\": \"write\", \"url\": \"/api/v1/orderOtherService/orderOther\", \"body\": \"{\\\"id\\\":\\\"0909b313-eeab-4463-a068-82f33d56cb49\\\",\\\"boughtDate\\\":\\\"2024-05-09 18:31:54\\\",\\\"travelDate\\\":\\\"2024-05-09\\\",\\\"travelTime\\\":\\\"2013-05-04 09:51:52\\\",\\\"accountId\\\":\\\"4d2a46c7-71cb-4cf1-b5bb-b68406d9da6f\\\",\\\"contactsName\\\":\\\"Contacts_One\\\",\\\"documentType\\\":1,\\\"contactsDocumentNumber\\\":\\\"DocumentNumber_One\\\",\\\"trainNumber\\\":\\\"Z1234\\\",\\\"coachNumber\\\":5,\\\"seatClass\\\":2,\\\"seatNumber\\\":\\\"145098254\\\",\\\"from\\\":\\\"shanghai\\\",\\\"to\\\":\\\"nanjing\\\",\\\"status\\\":4,\\\"price\\\":\\\"350.0\\\",\\\"differenceMoney\\\":\\\"0.0\\\"}\", \"method\": \"PUT\"}",
        "{\"type\": \"read\", \"url\": \"/api/v1/orderOtherService/orderOther/?\", \"body\": \"\", \"method\": \"GET\"}"
    ],
    "55": [
        "{\"type\": \"write\", \"url\": \"/api/v1/orderOtherService/orderOther\", \"body\": \"{\\\"id\\\":\\\"0909b313-eeab-4463-a068-82f33d56cb49\\\",\\\"boughtDate\\\":\\\"2024-05-09 18:31:54\\\",\\\"travelDate\\\":\\\"2024-05-09\\\",\\\"travelTime\\\":\\\"2013-05-04 09:51:52\\\",\\\"accountId\\\":\\\"4d2a46c7-71cb-4cf1-b5bb-b68406d9da6f\\\",\\\"contactsName\\\":\\\"Contacts_One\\\",\\\"documentType\\\":1,\\\"contactsDocumentNumber\\\":\\\"DocumentNumber_One\\\",\\\"trainNumber\\\":\\\"Z1234\\\",\\\"coachNumber\\\":5,\\\"seatClass\\\":2,\\\"seatNumber\\\":\\\"145098254\\\",\\\"from\\\":\\\"shanghai\\\",\\\"to\\\":\\\"nanjing\\\",\\\"status\\\":4,\\\"price\\\":\\\"350.0\\\",\\\"differenceMoney\\\":\\\"0.0\\\"}\", \"method\": \"PUT\"}",
        "{\"type\": \"read\", \"url\": \"/api/v1/paymentservice/payment\", \"body\": \"{\\\"id\\\":null,\\\"orderId\\\":\\\"0909b313-eeab-4463-a068-82f33d56cb49\\\",\\\"userId\\\":null,\\\"price\\\":\\\"350.0\\\",\\\"type\\\":null}\", \"method\": \"POST\"}"
    ],
    "56": [
        "{\"type\": \"write\", \"url\": \"/api/v1/orderOtherService/orderOther\", \"body\": \"{\\\"id\\\":\\\"0909b313-eeab-4463-a068-82f33d56cb49\\\",\\\"boughtDate\\\":\\\"2024-05-09 18:31:54\\\",\\\"travelDate\\\":\\\"2024-05-09\\\",\\\"travelTime\\\":\\\"2013-05-04 09:51:52\\\",\\\"accountId\\\":\\\"4d2a46c7-71cb-4cf1-b5bb-b68406d9da6f\\\",\\\"contactsName\\\":\\\"Contacts_One\\\",\\\"documentType\\\":1,\\\"contactsDocumentNumber\\\":\\\"DocumentNumber_One\\\",\\\"trainNumber\\\":\\\"Z1234\\\",\\\"coachNumber\\\":5,\\\"seatClass\\\":2,\\\"seatNumber\\\":\\\"145098254\\\",\\\"from\\\":\\\"shanghai\\\",\\\"to\\\":\\\"nanjing\\\",\\\"status\\\":4,\\\"price\\\":\\\"350.0\\\",\\\"differenceMoney\\\":\\\"0.0\\\"}\", \"method\": \"PUT\"}",
        "{\"type\": \"write\", \"url\": \"/api/v1/paymentservice/payment\", \"body\": \"{\\\"id\\\":null,\\\"orderId\\\":\\\"0909b313-eeab-4463-a068-82f33d56cb49\\\",\\\"userId\\\":null,\\\"price\\\":\\\"350.0\\\",\\\"type\\\":null}\", \"method\": \"POST\"}"
    ],
    "57": [
        "{\"type\": \"write\", \"url\": \"/api/v1/orderOtherService/orderOther\", \"body\": \"{\\\"id\\\":\\\"0909b313-eeab-4463-a068-82f33d56cb49\\\",\\\"boughtDate\\\":\\\"2024-05-09 18:31:54\\\",\\\"travelDate\\\":\\\"2024-05-09\\\",\\\"travelTime\\\":\\\"2013-05-04 09:51:52\\\",\\\"accountId\\\":\\\"4d2a46c7-71cb-4cf1-b5bb-b68406d9da6f\\\",\\\"contactsName\\\":\\\"Contacts_One\\\",\\\"documentType\\\":1,\\\"contactsDocumentNumber\\\":\\\"DocumentNumber_One\\\",\\\"trainNumber\\\":\\\"Z1234\\\",\\\"coachNumber\\\":5,\\\"seatClass\\\":2,\\\"seatNumber\\\":\\\"145098254\\\",\\\"from\\\":\\\"shanghai\\\",\\\"to\\\":\\\"nanjing\\\",\\\"status\\\":4,\\\"price\\\":\\\"350.0\\\",\\\"differenceMoney\\\":\\\"0.0\\\"}\", \"method\": \"PUT\"}",
        "{\"type\": \"write\", \"url\": \"/api/v1/inside_pay_service/inside_payment\", \"body\": \"\", \"method\": \"POST\"}"
    ],
    "58": [
        "{\"type\": \"write\", \"url\": \"/api/v1/orderOtherService/orderOther\", \"body\": \"{\\\"id\\\":\\\"0909b313-eeab-4463-a068-82f33d56cb49\\\",\\\"boughtDate\\\":\\\"2024-05-09 18:31:54\\\",\\\"travelDate\\\":\\\"2024-05-09\\\",\\\"travelTime\\\":\\\"2013-05-04 09:51:52\\\",\\\"accountId\\\":\\\"4d2a46c7-71cb-4cf1-b5bb-b68406d9da6f\\\",\\\"contactsName\\\":\\\"Contacts_One\\\",\\\"documentType\\\":1,\\\"contactsDocumentNumber\\\":\\\"DocumentNumber_One\\\",\\\"trainNumber\\\":\\\"Z1234\\\",\\\"coachNumber\\\":5,\\\"seatClass\\\":2,\\\"seatNumber\\\":\\\"145098254\\\",\\\"from\\\":\\\"shanghai\\\",\\\"to\\\":\\\"nanjing\\\",\\\"status\\\":4,\\\"price\\\":\\\"350.0\\\",\\\"differenceMoney\\\":\\\"0.0\\\"}\", \"method\": \"PUT\"}",
        "{\"type\": \"read\", \"url\": \"/api/v1/orderOtherService/orderOther/status/?/?\", \"body\": \"\", \"method\": \"GET\"}"
    ],
    "59": [
        "{\"type\": \"read\", \"url\": \"/api/v1/orderOtherService/orderOther/?\", \"body\": \"\", \"method\": \"GET\"}",
        "{\"type\": \"write\", \"url\": \"/api/v1/orderOtherService/orderOther\", \"body\": \"{\\\"id\\\":\\\"0909b313-eeab-4463-a068-82f33d56cb49\\\",\\\"boughtDate\\\":\\\"2024-05-09 18:31:54\\\",\\\"travelDate\\\":\\\"2024-05-09\\\",\\\"travelTime\\\":\\\"2013-05-04 09:51:52\\\",\\\"accountId\\\":\\\"4d2a46c7-71cb-4cf1-b5bb-b68406d9da6f\\\",\\\"contactsName\\\":\\\"Contacts_One\\\",\\\"documentType\\\":1,\\\"contactsDocumentNumber\\\":\\\"DocumentNumber_One\\\",\\\"trainNumber\\\":\\\"Z1234\\\",\\\"coachNumber\\\":5,\\\"seatClass\\\":2,\\\"seatNumber\\\":\\\"145098254\\\",\\\"from\\\":\\\"shanghai\\\",\\\"to\\\":\\\"nanjing\\\",\\\"status\\\":7,\\\"price\\\":\\\"350.0\\\",\\\"differenceMoney\\\":\\\"0.0\\\"}\", \"method\": \"PUT\"}"
    ],
    "60": [
        "{\"type\": \"read\", \"url\": \"/api/v1/orderOtherService/orderOther/?\", \"body\": \"\", \"method\": \"GET\"}",
        "{\"type\": \"write\", \"url\": \"/api/v1/paymentservice/payment\", \"body\": \"{\\\"id\\\":null,\\\"orderId\\\":\\\"0909b313-eeab-4463-a068-82f33d56cb49\\\",\\\"userId\\\":null,\\\"price\\\":\\\"350.0\\\",\\\"type\\\":null}\", \"method\": \"POST\"}"
    ],
    "61": [
        "{\"type\": \"read\", \"url\": \"/api/v1/orderOtherService/orderOther/?\", \"body\": \"\", \"method\": \"GET\"}",
        "{\"type\": \"write\", \"url\": \"/api/v1/inside_pay_service/inside_payment\", \"body\": \"\", \"method\": \"POST\"}"
    ],
    "62": [
        "{\"type\": \"read\", \"url\": \"/api/v1/orderOtherService/orderOther/?\", \"body\": \"\", \"method\": \"GET\"}",
        "{\"type\": \"write\", \"url\": \"/api/v1/orderOtherService/orderOther/status/?/?\", \"body\": \"\", \"method\": \"GET\"}"
    ],
    "63": [
        "{\"type\": \"read\", \"url\": \"/api/v1/orderOtherService/orderOther\", \"body\": \"{\\\"id\\\":\\\"0909b313-eeab-4463-a068-82f33d56cb49\\\",\\\"boughtDate\\\":\\\"2024-05-09 18:31:54\\\",\\\"travelDate\\\":\\\"2024-05-09\\\",\\\"travelTime\\\":\\\"2013-05-04 09:51:52\\\",\\\"accountId\\\":\\\"4d2a46c7-71cb-4cf1-b5bb-b68406d9da6f\\\",\\\"contactsName\\\":\\\"Contacts_One\\\",\\\"documentType\\\":1,\\\"contactsDocumentNumber\\\":\\\"DocumentNumber_One\\\",\\\"trainNumber\\\":\\\"Z1234\\\",\\\"coachNumber\\\":5,\\\"seatClass\\\":2,\\\"seatNumber\\\":\\\"145098254\\\",\\\"from\\\":\\\"shanghai\\\",\\\"to\\\":\\\"nanjing\\\",\\\"status\\\":7,\\\"price\\\":\\\"350.0\\\",\\\"differenceMoney\\\":\\\"0.0\\\"}\", \"method\": \"PUT\"}",
        "{\"type\": \"write\", \"url\": \"/api/v1/paymentservice/payment\", \"body\": \"{\\\"id\\\":null,\\\"orderId\\\":\\\"0909b313-eeab-4463-a068-82f33d56cb49\\\",\\\"userId\\\":null,\\\"price\\\":\\\"350.0\\\",\\\"type\\\":null}\", \"method\": \"POST\"}"
    ],
    "64": [
        "{\"type\": \"read\", \"url\": \"/api/v1/orderOtherService/orderOther\", \"body\": \"{\\\"id\\\":\\\"0909b313-eeab-4463-a068-82f33d56cb49\\\",\\\"boughtDate\\\":\\\"2024-05-09 18:31:54\\\",\\\"travelDate\\\":\\\"2024-05-09\\\",\\\"travelTime\\\":\\\"2013-05-04 09:51:52\\\",\\\"accountId\\\":\\\"4d2a46c7-71cb-4cf1-b5bb-b68406d9da6f\\\",\\\"contactsName\\\":\\\"Contacts_One\\\",\\\"documentType\\\":1,\\\"contactsDocumentNumber\\\":\\\"DocumentNumber_One\\\",\\\"trainNumber\\\":\\\"Z1234\\\",\\\"coachNumber\\\":5,\\\"seatClass\\\":2,\\\"seatNumber\\\":\\\"145098254\\\",\\\"from\\\":\\\"shanghai\\\",\\\"to\\\":\\\"nanjing\\\",\\\"status\\\":7,\\\"price\\\":\\\"350.0\\\",\\\"differenceMoney\\\":\\\"0.0\\\"}\", \"method\": \"PUT\"}",
        "{\"type\": \"write\", \"url\": \"/api/v1/inside_pay_service/inside_payment\", \"body\": \"\", \"method\": \"POST\"}"
    ],
    "65": [
        "{\"type\": \"read\", \"url\": \"/api/v1/orderOtherService/orderOther\", \"body\": \"{\\\"id\\\":\\\"0909b313-eeab-4463-a068-82f33d56cb49\\\",\\\"boughtDate\\\":\\\"2024-05-09 18:31:54\\\",\\\"travelDate\\\":\\\"2024-05-09\\\",\\\"travelTime\\\":\\\"2013-05-04 09:51:52\\\",\\\"accountId\\\":\\\"4d2a46c7-71cb-4cf1-b5bb-b68406d9da6f\\\",\\\"contactsName\\\":\\\"Contacts_One\\\",\\\"documentType\\\":1,\\\"contactsDocumentNumber\\\":\\\"DocumentNumber_One\\\",\\\"trainNumber\\\":\\\"Z1234\\\",\\\"coachNumber\\\":5,\\\"seatClass\\\":2,\\\"seatNumber\\\":\\\"145098254\\\",\\\"from\\\":\\\"shanghai\\\",\\\"to\\\":\\\"nanjing\\\",\\\"status\\\":7,\\\"price\\\":\\\"350.0\\\",\\\"differenceMoney\\\":\\\"0.0\\\"}\", \"method\": \"PUT\"}",
        "{\"type\": \"write\", \"url\": \"/api/v1/orderOtherService/orderOther/status/?/?\", \"body\": \"\", \"method\": \"GET\"}"
    ],
    "66": [
        "{\"type\": \"write\", \"url\": \"/api/v1/orderOtherService/orderOther\", \"body\": \"{\\\"id\\\":\\\"0909b313-eeab-4463-a068-82f33d56cb49\\\",\\\"boughtDate\\\":\\\"2024-05-09 18:31:54\\\",\\\"travelDate\\\":\\\"2024-05-09\\\",\\\"travelTime\\\":\\\"2013-05-04 09:51:52\\\",\\\"accountId\\\":\\\"4d2a46c7-71cb-4cf1-b5bb-b68406d9da6f\\\",\\\"contactsName\\\":\\\"Contacts_One\\\",\\\"documentType\\\":1,\\\"contactsDocumentNumber\\\":\\\"DocumentNumber_One\\\",\\\"trainNumber\\\":\\\"Z1234\\\",\\\"coachNumber\\\":5,\\\"seatClass\\\":2,\\\"seatNumber\\\":\\\"145098254\\\",\\\"from\\\":\\\"shanghai\\\",\\\"to\\\":\\\"nanjing\\\",\\\"status\\\":7,\\\"price\\\":\\\"350.0\\\",\\\"differenceMoney\\\":\\\"0.0\\\"}\", \"method\": \"PUT\"}",
        "{\"type\": \"read\", \"url\": \"/api/v1/inside_pay_service/inside_payment/drawback/?/?\", \"body\": \"\", \"method\": \"GET\"}"
    ],
    "67": [
        "{\"type\": \"write\", \"url\": \"/api/v1/orderOtherService/orderOther\", \"body\": \"{\\\"id\\\":\\\"0909b313-eeab-4463-a068-82f33d56cb49\\\",\\\"boughtDate\\\":\\\"2024-05-09 18:31:54\\\",\\\"travelDate\\\":\\\"2024-05-09\\\",\\\"travelTime\\\":\\\"2013-05-04 09:51:52\\\",\\\"accountId\\\":\\\"4d2a46c7-71cb-4cf1-b5bb-b68406d9da6f\\\",\\\"contactsName\\\":\\\"Contacts_One\\\",\\\"documentType\\\":1,\\\"contactsDocumentNumber\\\":\\\"DocumentNumber_One\\\",\\\"trainNumber\\\":\\\"Z1234\\\",\\\"coachNumber\\\":5,\\\"seatClass\\\":2,\\\"seatNumber\\\":\\\"145098254\\\",\\\"from\\\":\\\"shanghai\\\",\\\"to\\\":\\\"nanjing\\\",\\\"status\\\":7,\\\"price\\\":\\\"350.0\\\",\\\"differenceMoney\\\":\\\"0.0\\\"}\", \"method\": \"PUT\"}",
        "{\"type\": \"write\", \"url\": \"/api/v1/inside_pay_service/inside_payment/drawback/?/?\", \"body\": \"\", \"method\": \"GET\"}"
    ],
    "68": [
        "{\"type\": \"write\", \"url\": \"/api/v1/orderOtherService/orderOther\", \"body\": \"{\\\"id\\\":\\\"0909b313-eeab-4463-a068-82f33d56cb49\\\",\\\"boughtDate\\\":\\\"2024-05-09 18:31:54\\\",\\\"travelDate\\\":\\\"2024-05-09\\\",\\\"travelTime\\\":\\\"2013-05-04 09:51:52\\\",\\\"accountId\\\":\\\"4d2a46c7-71cb-4cf1-b5bb-b68406d9da6f\\\",\\\"contactsName\\\":\\\"Contacts_One\\\",\\\"documentType\\\":1,\\\"contactsDocumentNumber\\\":\\\"DocumentNumber_One\\\",\\\"trainNumber\\\":\\\"Z1234\\\",\\\"coachNumber\\\":5,\\\"seatClass\\\":2,\\\"seatNumber\\\":\\\"145098254\\\",\\\"from\\\":\\\"shanghai\\\",\\\"to\\\":\\\"nanjing\\\",\\\"status\\\":7,\\\"price\\\":\\\"350.0\\\",\\\"differenceMoney\\\":\\\"0.0\\\"}\", \"method\": \"PUT\"}",
        "{\"type\": \"read\", \"url\": \"/api/v1/orderservice/order/?\", \"body\": \"\", \"method\": \"GET\"}"
    ],
    "69": [
        "{\"type\": \"write\", \"url\": \"/api/v1/orderOtherService/orderOther\", \"body\": \"{\\\"id\\\":\\\"0909b313-eeab-4463-a068-82f33d56cb49\\\",\\\"boughtDate\\\":\\\"2024-05-09 18:31:54\\\",\\\"travelDate\\\":\\\"2024-05-09\\\",\\\"travelTime\\\":\\\"2013-05-04 09:51:52\\\",\\\"accountId\\\":\\\"4d2a46c7-71cb-4cf1-b5bb-b68406d9da6f\\\",\\\"contactsName\\\":\\\"Contacts_One\\\",\\\"documentType\\\":1,\\\"contactsDocumentNumber\\\":\\\"DocumentNumber_One\\\",\\\"trainNumber\\\":\\\"Z1234\\\",\\\"coachNumber\\\":5,\\\"seatClass\\\":2,\\\"seatNumber\\\":\\\"145098254\\\",\\\"from\\\":\\\"shanghai\\\",\\\"to\\\":\\\"nanjing\\\",\\\"status\\\":7,\\\"price\\\":\\\"350.0\\\",\\\"differenceMoney\\\":\\\"0.0\\\"}\", \"method\": \"PUT\"}",
        "{\"type\": \"read\", \"url\": \"/api/v1/orderOtherService/orderOther/?\", \"body\": \"\", \"method\": \"GET\"}"
    ],
    "70": [
        "{\"type\": \"write\", \"url\": \"/api/v1/orderOtherService/orderOther\", \"body\": \"{\\\"id\\\":\\\"0909b313-eeab-4463-a068-82f33d56cb49\\\",\\\"boughtDate\\\":\\\"2024-05-09 18:31:54\\\",\\\"travelDate\\\":\\\"2024-05-09\\\",\\\"travelTime\\\":\\\"2013-05-04 09:51:52\\\",\\\"accountId\\\":\\\"4d2a46c7-71cb-4cf1-b5bb-b68406d9da6f\\\",\\\"contactsName\\\":\\\"Contacts_One\\\",\\\"documentType\\\":1,\\\"contactsDocumentNumber\\\":\\\"DocumentNumber_One\\\",\\\"trainNumber\\\":\\\"Z1234\\\",\\\"coachNumber\\\":5,\\\"seatClass\\\":2,\\\"seatNumber\\\":\\\"145098254\\\",\\\"from\\\":\\\"shanghai\\\",\\\"to\\\":\\\"nanjing\\\",\\\"status\\\":7,\\\"price\\\":\\\"350.0\\\",\\\"differenceMoney\\\":\\\"0.0\\\"}\", \"method\": \"PUT\"}",
        "{\"type\": \"read\", \"url\": \"/api/v1/orderOtherService/orderOther/?\", \"body\": \"\", \"method\": \"GET\"}"
    ],
    "71": [
        "{\"type\": \"write\", \"url\": \"/api/v1/orderOtherService/orderOther\", \"body\": \"{\\\"id\\\":\\\"0909b313-eeab-4463-a068-82f33d56cb49\\\",\\\"boughtDate\\\":\\\"2024-05-09 18:31:54\\\",\\\"travelDate\\\":\\\"2024-05-09\\\",\\\"travelTime\\\":\\\"2013-05-04 09:51:52\\\",\\\"accountId\\\":\\\"4d2a46c7-71cb-4cf1-b5bb-b68406d9da6f\\\",\\\"contactsName\\\":\\\"Contacts_One\\\",\\\"documentType\\\":1,\\\"contactsDocumentNumber\\\":\\\"DocumentNumber_One\\\",\\\"trainNumber\\\":\\\"Z1234\\\",\\\"coachNumber\\\":5,\\\"seatClass\\\":2,\\\"seatNumber\\\":\\\"145098254\\\",\\\"from\\\":\\\"shanghai\\\",\\\"to\\\":\\\"nanjing\\\",\\\"status\\\":7,\\\"price\\\":\\\"350.0\\\",\\\"differenceMoney\\\":\\\"0.0\\\"}\", \"method\": \"PUT\"}",
        "{\"type\": \"read\", \"url\": \"/api/v1/orderOtherService/orderOther/?\", \"body\": \"\", \"method\": \"GET\"}"
    ],
    "72": [
        "{\"type\": \"write\", \"url\": \"/api/v1/orderOtherService/orderOther\", \"body\": \"{\\\"id\\\":\\\"0909b313-eeab-4463-a068-82f33d56cb49\\\",\\\"boughtDate\\\":\\\"2024-05-09 18:31:54\\\",\\\"travelDate\\\":\\\"2024-05-09\\\",\\\"travelTime\\\":\\\"2013-05-04 09:51:52\\\",\\\"accountId\\\":\\\"4d2a46c7-71cb-4cf1-b5bb-b68406d9da6f\\\",\\\"contactsName\\\":\\\"Contacts_One\\\",\\\"documentType\\\":1,\\\"contactsDocumentNumber\\\":\\\"DocumentNumber_One\\\",\\\"trainNumber\\\":\\\"Z1234\\\",\\\"coachNumber\\\":5,\\\"seatClass\\\":2,\\\"seatNumber\\\":\\\"145098254\\\",\\\"from\\\":\\\"shanghai\\\",\\\"to\\\":\\\"nanjing\\\",\\\"status\\\":7,\\\"price\\\":\\\"350.0\\\",\\\"differenceMoney\\\":\\\"0.0\\\"}\", \"method\": \"PUT\"}",
        "{\"type\": \"read\", \"url\": \"/api/v1/paymentservice/payment\", \"body\": \"{\\\"id\\\":null,\\\"orderId\\\":\\\"0909b313-eeab-4463-a068-82f33d56cb49\\\",\\\"userId\\\":null,\\\"price\\\":\\\"350.0\\\",\\\"type\\\":null}\", \"method\": \"POST\"}"
    ],
    "73": [
        "{\"type\": \"write\", \"url\": \"/api/v1/orderOtherService/orderOther\", \"body\": \"{\\\"id\\\":\\\"0909b313-eeab-4463-a068-82f33d56cb49\\\",\\\"boughtDate\\\":\\\"2024-05-09 18:31:54\\\",\\\"travelDate\\\":\\\"2024-05-09\\\",\\\"travelTime\\\":\\\"2013-05-04 09:51:52\\\",\\\"accountId\\\":\\\"4d2a46c7-71cb-4cf1-b5bb-b68406d9da6f\\\",\\\"contactsName\\\":\\\"Contacts_One\\\",\\\"documentType\\\":1,\\\"contactsDocumentNumber\\\":\\\"DocumentNumber_One\\\",\\\"trainNumber\\\":\\\"Z1234\\\",\\\"coachNumber\\\":5,\\\"seatClass\\\":2,\\\"seatNumber\\\":\\\"145098254\\\",\\\"from\\\":\\\"shanghai\\\",\\\"to\\\":\\\"nanjing\\\",\\\"status\\\":7,\\\"price\\\":\\\"350.0\\\",\\\"differenceMoney\\\":\\\"0.0\\\"}\", \"method\": \"PUT\"}",
        "{\"type\": \"write\", \"url\": \"/api/v1/paymentservice/payment\", \"body\": \"{\\\"id\\\":null,\\\"orderId\\\":\\\"0909b313-eeab-4463-a068-82f33d56cb49\\\",\\\"userId\\\":null,\\\"price\\\":\\\"350.0\\\",\\\"type\\\":null}\", \"method\": \"POST\"}"
    ],
    "74": [
        "{\"type\": \"write\", \"url\": \"/api/v1/orderOtherService/orderOther\", \"body\": \"{\\\"id\\\":\\\"0909b313-eeab-4463-a068-82f33d56cb49\\\",\\\"boughtDate\\\":\\\"2024-05-09 18:31:54\\\",\\\"travelDate\\\":\\\"2024-05-09\\\",\\\"travelTime\\\":\\\"2013-05-04 09:51:52\\\",\\\"accountId\\\":\\\"4d2a46c7-71cb-4cf1-b5bb-b68406d9da6f\\\",\\\"contactsName\\\":\\\"Contacts_One\\\",\\\"documentType\\\":1,\\\"contactsDocumentNumber\\\":\\\"DocumentNumber_One\\\",\\\"trainNumber\\\":\\\"Z1234\\\",\\\"coachNumber\\\":5,\\\"seatClass\\\":2,\\\"seatNumber\\\":\\\"145098254\\\",\\\"from\\\":\\\"shanghai\\\",\\\"to\\\":\\\"nanjing\\\",\\\"status\\\":7,\\\"price\\\":\\\"350.0\\\",\\\"differenceMoney\\\":\\\"0.0\\\"}\", \"method\": \"PUT\"}",
        "{\"type\": \"write\", \"url\": \"/api/v1/inside_pay_service/inside_payment\", \"body\": \"\", \"method\": \"POST\"}"
    ],
    "75": [
        "{\"type\": \"write\", \"url\": \"/api/v1/orderOtherService/orderOther\", \"body\": \"{\\\"id\\\":\\\"0909b313-eeab-4463-a068-82f33d56cb49\\\",\\\"boughtDate\\\":\\\"2024-05-09 18:31:54\\\",\\\"travelDate\\\":\\\"2024-05-09\\\",\\\"travelTime\\\":\\\"2013-05-04 09:51:52\\\",\\\"accountId\\\":\\\"4d2a46c7-71cb-4cf1-b5bb-b68406d9da6f\\\",\\\"contactsName\\\":\\\"Contacts_One\\\",\\\"documentType\\\":1,\\\"contactsDocumentNumber\\\":\\\"DocumentNumber_One\\\",\\\"trainNumber\\\":\\\"Z1234\\\",\\\"coachNumber\\\":5,\\\"seatClass\\\":2,\\\"seatNumber\\\":\\\"145098254\\\",\\\"from\\\":\\\"shanghai\\\",\\\"to\\\":\\\"nanjing\\\",\\\"status\\\":7,\\\"price\\\":\\\"350.0\\\",\\\"differenceMoney\\\":\\\"0.0\\\"}\", \"method\": \"PUT\"}",
        "{\"type\": \"read\", \"url\": \"/api/v1/orderOtherService/orderOther/status/?/?\", \"body\": \"\", \"method\": \"GET\"}"
    ],
    "76": [
        "{\"type\": \"read\", \"url\": \"/api/v1/inside_pay_service/inside_payment/drawback/?/?\", \"body\": \"\", \"method\": \"GET\"}",
        "{\"type\": \"write\", \"url\": \"/api/v1/orderOtherService/orderOther/status/?/?\", \"body\": \"\", \"method\": \"GET\"}"
    ],
    "77": [
        "{\"type\": \"write\", \"url\": \"/api/v1/inside_pay_service/inside_payment/drawback/?/?\", \"body\": \"\", \"method\": \"GET\"}",
        "{\"type\": \"write\", \"url\": \"/api/v1/orderOtherService/orderOther/status/?/?\", \"body\": \"\", \"method\": \"GET\"}"
    ],
    "78": [
        "{\"type\": \"read\", \"url\": \"/api/v1/orderservice/order/?\", \"body\": \"\", \"method\": \"GET\"}",
        "{\"type\": \"write\", \"url\": \"/api/v1/paymentservice/payment\", \"body\": \"{\\\"id\\\":null,\\\"orderId\\\":\\\"0909b313-eeab-4463-a068-82f33d56cb49\\\",\\\"userId\\\":null,\\\"price\\\":\\\"350.0\\\",\\\"type\\\":null}\", \"method\": \"POST\"}"
    ],
    "79": [
        "{\"type\": \"read\", \"url\": \"/api/v1/orderservice/order/?\", \"body\": \"\", \"method\": \"GET\"}",
        "{\"type\": \"write\", \"url\": \"/api/v1/inside_pay_service/inside_payment\", \"body\": \"\", \"method\": \"POST\"}"
    ],
    "80": [
        "{\"type\": \"read\", \"url\": \"/api/v1/orderservice/order/?\", \"body\": \"\", \"method\": \"GET\"}",
        "{\"type\": \"write\", \"url\": \"/api/v1/orderOtherService/orderOther/status/?/?\", \"body\": \"\", \"method\": \"GET\"}"
    ],
    "81": [
        "{\"type\": \"read\", \"url\": \"/api/v1/orderOtherService/orderOther/?\", \"body\": \"\", \"method\": \"GET\"}",
        "{\"type\": \"write\", \"url\": \"/api/v1/paymentservice/payment\", \"body\": \"{\\\"id\\\":null,\\\"orderId\\\":\\\"0909b313-eeab-4463-a068-82f33d56cb49\\\",\\\"userId\\\":null,\\\"price\\\":\\\"350.0\\\",\\\"type\\\":null}\", \"method\": \"POST\"}"
    ],
    "82": [
        "{\"type\": \"read\", \"url\": \"/api/v1/orderOtherService/orderOther/?\", \"body\": \"\", \"method\": \"GET\"}",
        "{\"type\": \"write\", \"url\": \"/api/v1/inside_pay_service/inside_payment\", \"body\": \"\", \"method\": \"POST\"}"
    ],
    "83": [
        "{\"type\": \"read\", \"url\": \"/api/v1/orderOtherService/orderOther/?\", \"body\": \"\", \"method\": \"GET\"}",
        "{\"type\": \"write\", \"url\": \"/api/v1/orderOtherService/orderOther/status/?/?\", \"body\": \"\", \"method\": \"GET\"}"
    ],
    "84": [
        "{\"type\": \"read\", \"url\": \"/api/v1/orderOtherService/orderOther/?\", \"body\": \"\", \"method\": \"GET\"}",
        "{\"type\": \"write\", \"url\": \"/api/v1/paymentservice/payment\", \"body\": \"{\\\"id\\\":null,\\\"orderId\\\":\\\"0909b313-eeab-4463-a068-82f33d56cb49\\\",\\\"userId\\\":null,\\\"price\\\":\\\"350.0\\\",\\\"type\\\":null}\", \"method\": \"POST\"}"
    ],
    "85": [
        "{\"type\": \"read\", \"url\": \"/api/v1/orderOtherService/orderOther/?\", \"body\": \"\", \"method\": \"GET\"}",
        "{\"type\": \"write\", \"url\": \"/api/v1/inside_pay_service/inside_payment\", \"body\": \"\", \"method\": \"POST\"}"
    ],
    "86": [
        "{\"type\": \"read\", \"url\": \"/api/v1/orderOtherService/orderOther/?\", \"body\": \"\", \"method\": \"GET\"}",
        "{\"type\": \"write\", \"url\": \"/api/v1/orderOtherService/orderOther/status/?/?\", \"body\": \"\", \"method\": \"GET\"}"
    ],
    "87": [
        "{\"type\": \"read\", \"url\": \"/api/v1/orderOtherService/orderOther/?\", \"body\": \"\", \"method\": \"GET\"}",
        "{\"type\": \"write\", \"url\": \"/api/v1/paymentservice/payment\", \"body\": \"{\\\"id\\\":null,\\\"orderId\\\":\\\"0909b313-eeab-4463-a068-82f33d56cb49\\\",\\\"userId\\\":null,\\\"price\\\":\\\"350.0\\\",\\\"type\\\":null}\", \"method\": \"POST\"}"
    ],
    "88": [
        "{\"type\": \"read\", \"url\": \"/api/v1/orderOtherService/orderOther/?\", \"body\": \"\", \"method\": \"GET\"}",
        "{\"type\": \"write\", \"url\": \"/api/v1/orderOtherService/orderOther/status/?/?\", \"body\": \"\", \"method\": \"GET\"}"
    ],
    "89": [
        "{\"type\": \"read\", \"url\": \"/api/v1/paymentservice/payment\", \"body\": \"{\\\"id\\\":null,\\\"orderId\\\":\\\"0909b313-eeab-4463-a068-82f33d56cb49\\\",\\\"userId\\\":null,\\\"price\\\":\\\"350.0\\\",\\\"type\\\":null}\", \"method\": \"POST\"}",
        "{\"type\": \"write\", \"url\": \"/api/v1/orderOtherService/orderOther/status/?/?\", \"body\": \"\", \"method\": \"GET\"}"
    ],
    "90": [
        "{\"type\": \"write\", \"url\": \"/api/v1/paymentservice/payment\", \"body\": \"{\\\"id\\\":null,\\\"orderId\\\":\\\"0909b313-eeab-4463-a068-82f33d56cb49\\\",\\\"userId\\\":null,\\\"price\\\":\\\"350.0\\\",\\\"type\\\":null}\", \"method\": \"POST\"}",
        "{\"type\": \"read\", \"url\": \"/api/v1/orderOtherService/orderOther/status/?/?\", \"body\": \"\", \"method\": \"GET\"}"
    ],
    "91": [
        "{\"type\": \"write\", \"url\": \"/api/v1/paymentservice/payment\", \"body\": \"{\\\"id\\\":null,\\\"orderId\\\":\\\"0909b313-eeab-4463-a068-82f33d56cb49\\\",\\\"userId\\\":null,\\\"price\\\":\\\"350.0\\\",\\\"type\\\":null}\", \"method\": \"POST\"}",
        "{\"type\": \"write\", \"url\": \"/api/v1/orderOtherService/orderOther/status/?/?\", \"body\": \"\", \"method\": \"GET\"}"
    ]
}